Workbook

Sheet Plurmits-All Plurmits
A1: Plurmit | B1: Department | C1: Annual volume of submissions | D1: Does this plurmit apply to businesses? | E1: Online Status [Normalized] | F1: Worth Integrating or Mentioning? | G1: Notes on integration/mention analysis | H1: Is it Integrated or mentioned yet? | I1: Link to CMS if mentioned *TLC: Don't use this column: use the Consumer Affairs Licenses column | J1: Relevant ADO tickets to Integration or Mention (Optional) | K1: Where is it (going to be) located? [MUNI] | L1: Does this still need to be implemented for Oscars? [MUNI] | M1: Does it apply to Business.NJ.gov users? [MUNI] | N1: Mentioned on Business.NJ.gov? [MUNI] | O1: Industry/Sector Notes [MUNI] | P1: Municipality or LEA dependent? [MUNI] | Q1: Can it be integrated? (R and/or RW) [MUNI] | R1: Agency/Division | S1: Source | T1: Link/URL to viewable/ downloadable form (e.g., PDF) | U1: If applicable: Link/URL to website where the form can be completed and submitted online | V1: OFFICIAL FORM NUMBER (IF ASSIGNED) | W1: ONLINE FILING Y/N FROM PAST RESPONSE | X1: How does the user find the application form? (Online/Phone/Mail/In Person) | Y1: How does the user submit the form? (Online/Mail/Email/In Person) | Z1: If this form is online, what plaform/service is it hosted on? | AA1: If there is a fee, what is the fee to submit this form? | AB1: If there is a fee, what is the fee to submit this form? [Removed nulls] | AC1: If there is a fee, what is the fee to submit this form? [Normalized] | AD1: If the form needs the involvement of a notary/inspector/consultant/certified third party to be completed, please indicate the third party. | AE1: If the form needs the involvement of a notary/inspector/consultant/certified third party to be completed, please indicate the third party. [Normalized] | AF1: If there is a regulation or unsupported requirement (engineering drawing) preventing this form from being moved online, what is it? | AG1: If there is a regulation or unsupported requirement (engineering drawing) preventing this form from being moved online, what is it? [Normalized] | AH1: If it has some, what is the FAQ/copy/instructions for this form or group of forms? (provide URL if possible) | AI1: ➡️ ADDITIONAL NOTES | AJ1: Make an in-person request | AK1: On average, what percentage of form submissions end up rejected or sent back with errors? | AL1: What is the average processing time for this form? (In terms of hours:days) | AM1: The form is trackable online | AN1: Users receive an SMS | AO1: Make a request by calling our office | AP1: What is the total number of staff who handle: the review of, or approval/rejection of this form? | AQ1: Does this form have a regulatory timeframe? | AR1: Make a request through email/chat service | AS1: Do you notify users about information related to the status of their form? | AT1: What are the common reasons that forms are rejected? | AU1: For Column G "annual volume of form submissions," specify date range if complete data for Aug 2021 - Aug 2020 is not available. | AV1: Is there a fee associated with the submission of the form? | AW1: What is the annual volume of form submissions? [Integer] (CA) | AX1: Top 30: Law & Public Safety Survey 2019 | AY1: Query Identifier (from Dev pull) | AZ1: MLO Profession (using Boomi) | BA1: Task Exists, Integration Needed by Dev (as of 10 May 2024) | BB1: Reinstatement | BC1: MLO License Type # | BD1: Renewal | BE1: Task in CMS (main license application) [ARCHIVED] | BF1: Obtained by | BG1: Dyn. Applic. Type | BH1: Applies to Business (not individual)? (Regina's guesses) [TLC] | BI1: Database/System | BJ1: Legalized Games Category | BK1: Assigned initial review [TLC] | BL1: Consumer Affairs Licenses in CMS | BM1: Notes Consumer Affairs [TLC] | BN1: Industry [MUNI] | BO1: Industry Sector [MUNI] | BP1: [ECO] - PLURmit Purpose | BQ1: [ECO] - DEP Media Area | BR1: [ECO] - Current URL | BS1: Total Number of Licensees | BT1: Relates to B.NJ Industry | BU1: [ECO] - PLURmit Type | BV1: [ECO] - DEP System | BW1: Business Activity & Equipment | BX1: Business Activity & Equipment 2
A2: Sales Tax | B2: Department of the Treasury | C2: 866606 | D2: Yes this is a business/shop plurmit | F2: High Priority Integration, lacking agency buy-in | G2: We would love to integrate but Treasury does not want to as of Aug 26 2024. This is technically for the quarterly taxes, while ST-51 is for monthly taxes. We also have this in the CMS that covers the monthly taxes: https://dev.account.business.nj.gov/mgmt/cms#/collections/filings/entries/st-51_451 | H2: Read | I2: https://dev.account.business.nj.gov/mgmt/cms#/collections/filings/entries/st-50_450 | R2: Division of Taxation | S2: 2021 Permit List | U2: https://www1.state.nj.us/TYTR_BusinessFilings/jsp/common/Login.jsp?taxcode=55 | V2: ST-50; ST-50B; ST-450; ST-450B | X2: Online,Phone | Y2: Online | Z2: DORES Web Portal & AXWAY (3rd party software vendor) | AJ2: Yes | AK2: Cannot provide rejection counts due to daily changes. | AL2: Instantaneous | AM2: Yes | AN2: No | AO2: Yes | AP2: DORES | AQ2: Yes | AR2: Yes | AS2: No | AT2: Registration, Data Integrity, Calculation | AU2: 2020 | AV2: No | BH2: Yes
A3: Annual Report | B3: Department of the Treasury | C3: 667592 | D3: Yes this is a business/shop plurmit | F3: Yes - High Priority Integration | G3: 2021 667592 2022 705533 2023 752488 2024 786413 | H3: Read | I3: https://dev.account.business.nj.gov/mgmt/cms#/collections/filings/entries/annual-report | K3: Evergreen | BH3: Yes
A4: Producer Company Appointment/Termination Fee | B4: Department of Banking and Insurance | C4: 467251 | D4: Yes, but primarily used by large businesses | E4: Submitted | F4: No | G4: out of scope for BizX, this is focused on large insurance companies rather than SMBs | H4: No | S4: Combined data from 2018 and 2021 | T4: www.nipr.com | W4: Y | X4: Online | Y4: Online | AC4: No | AE4: No | AG4: No | AI4: INS
A5: New Jersey Partnership Return Gross Income Tax | B5: Department of the Treasury | C5: 253286 | D5: Yes this is a business/shop plurmit | F5: Yes - High Priority Integration | G5: We would love to integrate but Treasury does not want to as of Aug 26 2024 | H5: Read | I5: https://dev.account.business.nj.gov/mgmt/cms#/collections/filings/entries/nj-1065 | R5: Division of Taxation | S5: 2021 Permit List | T5: https://nj.gov/treasury/taxation/prntpart.shtml | U5: https://www1.state.nj.us/TYTR_BusinessFilings/jsp/common/Login.jsp?taxcode=43 | V5: NJ-1065 | X5: Online | Y5: In Person,Online,Mail | Z5: DORES Web Portal & AXWAY (3rd party software vendor) | AJ5: Yes | AK5: Cannot provide rejection counts due to daily changes. | AL5: Instantaneous | AM5: Yes | AN5: No | AO5: Yes | AQ5: Yes | AR5: Yes | AS5: No | AT5: Registration, Data Integrity, Calculation | AU5: 2019 | AV5: No | BH5: Yes
A6: Statement of Estimated Tax for Corporations | B6: Department of the Treasury | C6: 208969 | D6: Yes this is a business/shop plurmit | F6: Yes - Mention but not Integrate | G6: We would love to integrate but Treasury does not want to as of Aug 26 2024 | H6: Read | I6: https://dev.account.business.nj.gov/mgmt/cms#/collections/filings/entries/cbt-150 | R6: Division of Taxation | S6: 2021 Permit List | T6: https://nj.gov/treasury/taxation/prntcbt.shtml | U6: https://www1.state.nj.us/TYTR_BusinessFilings/jsp/common/Login.jsp?taxcode=20 | V6: CBT-150 | X6: Online | Y6: Online | Z6: DORES Web Portal & AXWAY (3rd party software vendor) | AJ6: Yes | AK6: Cannot provide rejection counts due to daily changes. | AL6: Instantaneous | AM6: Yes | AN6: No | AO6: Yes | AQ6: Yes | AR6: Yes | AS6: No | AT6: Registration, Data Integrity, Calculation | AU6: 2019 | AV6: No | BH6: Yes
A7: Weights and Measures Device Registration Certification (Devices) | B7: Department of Law and Public Safety | C7: 188109 | D7: Yes this is a business/shop plurmit | E7: Available | F7: Yes - Mention but not Integrate | G7: We have access to some data on weights and measures, but it may be a challenge to discern how to use it without a walkthrough from Consumer Affairs | H7: Mentioned | S7: Combined data from 2018 and 2021 | T7: https://www.njconsumeraffairs.gov/OWM/Applications/Registration-Application-for-Commercial-Weighing-and-Measuring-Devices.pdf | W7: N | X7: In person,Mail,Online | Y7: In person,Mail | Z7: DCA Website | AA7: Varies based on type of device | AB7: Varies based on type of device | AC7: Yes | AE7: No | AG7: No | BH7: Yes | BK7: RL | BL7: "weights-measures-registration - Register a Scale, Meter, or Other Weighing and Measuring Device for Your Business"
A8: Saltwater Angler - Individual Registration | B8: Department of Environmental Protection | C8: 160000 | D8: No, this is for municipalities or residents but not businesses | E8: Submitted | F8: No | G8: Called two charter boat companies in NJ, and customers are covered under the Captain's Saltwater Registry - For Hire Vessel registry record - Also connected with Katie from the NJDEP - Fish & Wildlife and stated there are ~1050 for-hire registrations this year - Bait and tackle shop employees could fall under retail, but unclear if that means the owner of the shop needs this permit. Even if so, this seems like a rare use case. | H8: N/A | S8: Combined data from 2018 and 2021 | T8: https://www.nj.gov/dep/online/ | U8: https://www.nj.gov/dep/online/ | X8: Online | Y8: Online | Z8: DEP Online | AC8: No | AE8: No | AG8: No | AH8: https://www.nj.gov/dep/online/ | BP8: From site: The New Jersey Department of Environmental Protection established the New Jersey Saltwater Recreational Registry Program to exempt saltwater recreational anglers fishing in New Jersey’s marine and tidal waters from the federal registry and the $15.00 federal registration fee imposed in 2011. The Department of Environmental Protection (DEP) implemented the New Jersey Saltwater Recreational Registry Program (NJSRRP) effective May 4, 2011 through Administrative Order No. 2011-05 . Who Needs to Register? NOTE: Anglers with a valid registration with the National Saltwater Angler Registry or have a valid license from another exempted state are required to register (for free) with the NJ Saltwater Recreational Registry Program. Registration with NJ will exempt you from having to register with the National Saltwater Angler Registry. Individual saltwater anglers ages 16 and older MUST register if ANY of the following criteria are met: - Recreationally fish with a hand line or rod and line, spearfish or fish by hand - Recreationally fish in the marine and fresh tidal waters of the State of New Jersey - Recreationally fish in marine waters outside the State of New Jersey but land the catch in New Jersey Individual saltwater anglers are EXEMPT from registering if either of the following apply: - Under the age of 16 - Solely fish on for-hire (party and charter) vessels that are registered with the New Jersey Saltwater Recreational Registry Program For-hire vessel owners/operators MUST register if: - Carry individuals who engage in recreational fishing in the marine and fresh tidal waters of the State of New Jersey OR - Carry individuals who engage in recreational fishing in the marine waters outside the State of New Jersey but land their catch in New Jersey From chat GPT: In New Jersey, specific businesses require a Saltwater Angler registration to legally engage in saltwater fishing activities. These businesses include: 1. Charter Boats and Party Boats: Companies offering chartered fishing trips or party boat services where patrons pay to fish in New Jersey's marine and estuarine waters. 2. Tackle Shops: Retailers that sell fishing equipment and may provide guidance or services related to saltwater fishing. 3. Marinas: Facilities that offer boat docking, storage, and other services for recreational fishing vessels. 4. Fishing Guides: Professional guides who lead fishing expeditions for clients in saltwater areas. The following types of businesses and their associated individuals require individual Saltwater Angler registration if they engage in recreational saltwater fishing: 1. Charter and Party Boat Operators: Captains and crew members who participate in fishing activities on charter or party boats. 2. Fishing Guides: Individuals who provide professional fishing guide services for recreational fishing in saltwater. 3. Commercial Fishermen Engaged in Recreational Fishing: Individuals who typically work in commercial fishing but also engage in recreational saltwater fishing. 4. Bait and Tackle Shop Employees: Employees who fish recreationally and may assist customers with fishing-related activities and guidance. 5. Marina Employees: Staff at marinas who fish recreationally and may assist boaters with fishing-related needs. | BQ8: Fish & Wildlife | BR8: https://dep.nj.gov/njfw/fishing/marine/saltwater-registry/ | BU8: Individual Registration | BV8: Data stored in another DEP-owned system
A9: Business Formation | B9: Department of the Treasury | C9: 140880 | D9: Yes this is a business/shop plurmit | F9: Yes - High Priority Integration | G9: Integrated | H9: Read and/or Write | R9: Division of Revenue and Enterprise Services | S9: Combined Data from 2018 and 2021 | T9: nj.gov/njbgs | U9: nj.gov/njbgs | V9: no | X9: In Person,Online,Mail,Phone,Email | Y9: In Person,Online,Mail,Email,Fax | Z9: NICUSA | AA9: 125 | AB9: 125 | AC9: Yes | AE9: No | AG9: No | AJ9: Yes | AK9: 2% (paper only) | AL9: Electronic, instantaneous; 5 business days, paper | AM9: Yes | AN9: No | AO9: Yes | AP9: 6 | AQ9: No | AR9: Yes | AS9: Yes | AT9: Incomplete/non-compliance with statutory/regualtory filing requirements | AU9: 9/1/2020-8/31/2021 | AV9: Yes | BH9: Yes | BK9: RL
A10: Business Registration (Integrates legal formation, tax registration and employer registration) | B10: Department of the Treasury | C10: 140544 | D10: Yes this is a business/shop plurmit | F10: Yes - High Priority Integration | G10: Partly integrated, we support validation not yet submission. | H10: Read | R10: Division of Revenue and Enterprise Services | S10: 2021 Permit List | T10: nj.gov/njbgs | U10: nj.gov/njbgs | V10: NJ REG | X10: In Person,Online,Mail,Phone,Email | Y10: In Person,Online,Mail,Email,Fax | Z10: NICUSA | AA10: 0 | AJ10: Yes | AK10: 2.5% (paper only) | AL10: Electronic, 2 business days; 10 business days, paper | AM10: Yes | AN10: No | AO10: Yes | AP10: 2.25 | AQ10: No | AR10: Yes | AS10: Yes | AT10: Incomplete/non-compliance with statutory/regualtory filing requirements | AU10: 8/26/2020 - 8/25/2021 | AV10: No | BH10: Yes | BK10: RL
A11: New Jersey S Corporation Business Tax Return | B11: Department of the Treasury | C11: 111701 | D11: Yes this is a business/shop plurmit | F11: Yes - Mention but not Integrate | G11: We would love to integrate but Treasury does not want to as of Aug 26 2024 | H11: Read | I11: https://dev.account.business.nj.gov/mgmt/cms#/collections/filings/entries/cbt-100s-final | R11: Division of Taxation | S11: 2021 Permit List | T11: https://nj.gov/treasury/taxation/prntcbt.shtml | U11: https://www.njportal.com/taxation/CBT | V11: CBT-100S | X11: Online | Y11: Online | Z11: DORES Web Portal & AXWAY (3rd party software vendor) | AJ11: Yes | AK11: Cannot provide rejection counts due to daily changes. | AL11: Instantaneous | AM11: Yes | AN11: No | AO11: Yes | AQ11: Yes | AR11: Yes | AS11: No | AT11: Registration, Data Integrity, Calculation | AU11: 2019 | AV11: No | BH11: Yes | BK11: RL
A12: Tentative Return and Application for Extension of Time to File Return | B12: Department of the Treasury | C12: 105458 | D12: Yes this is a business/shop plurmit | F12: Yes - Mention but not Integrate | H12: Read | I12: https://dev.account.business.nj.gov/mgmt/cms#/collections/filings/entries/cbt-200-t | R12: Division of Taxation | S12: 2021 Permit List | T12: https://nj.gov/treasury/taxation/prntcbt.shtml | U12: https://www1.state.nj.us/TYTR_BusinessFilings/jsp/common/Login.jsp?taxcode=20 | V12: CBT-200 | X12: Online | Y12: Online | Z12: DORES Web Portal & AXWAY (3rd party software vendor) | AI12: We already mention 100 and 100S in our system | AJ12: Yes | AK12: Cannot provide rejection counts due to daily changes. | AL12: Instantaneous | AM12: Yes | AN12: No | AO12: Yes | AQ12: Yes | AR12: Yes | AS12: No | AT12: Registration, Data Integrity, Calculation | AU12: 2019 | AV12: No | BH12: Yes | BK12: RL
A13: New Jersey Corporation Business Tax Return | B13: Department of the Treasury | C13: 104421 | D13: Yes this is a business/shop plurmit | F13: High Priority Integration, lacking agency buy-in | H13: Read | I13: https://dev.account.business.nj.gov/mgmt/cms#/collections/filings/entries/cbt-100_100u | R13: Division of Taxation | S13: 2021 Permit List | T13: https://nj.gov/treasury/taxation/prntcbt.shtml | U13: https://www.njportal.com/taxation/CBT | V13: CBT-100 | X13: Online | Y13: Online | Z13: DORES Web Portal & AXWAY (3rd party software vendor) | AJ13: Yes | AK13: Cannot provide rejection counts due to daily changes. | AL13: Instantaneous | AM13: Yes | AN13: No | AO13: Yes | AQ13: Yes | AR13: Yes | AS13: No | AT13: Registration, Data Integrity, Calculation | AU13: 2019 | AV13: No | BH13: Yes | BK13: RL
A14: Saltwater Angler - Review/Edit Current Registration | B14: Department of Environmental Protection | C14: 100000 | D14: No, this is for municipalities or residents but not businesses | E14: Submitted | F14: No | G14: Called two charter boat companies in NJ, and customers are covered under the Captain's Saltwater Registry - For Hire Vessel registry record - Also connected with Katie from the NJDEP - Fish & Wildlife and stated there are ~1050 for-hire registrations this year - Bait and tackle shop employees could fall under retail, but unclear if that means the owner of the shop needs this permit. Even if so, this seems like a rare use case. | H14: N/A | S14: Combined data from 2018 and 2021 | T14: https://www.nj.gov/dep/online/ | U14: https://www.nj.gov/dep/online/ | X14: Online | Y14: Online | Z14: DEP Online | AC14: No | AE14: No | AG14: No | AH14: https://www.nj.gov/dep/online/ | BP14: From site: The New Jersey Department of Environmental Protection established the New Jersey Saltwater Recreational Registry Program to exempt saltwater recreational anglers fishing in New Jersey’s marine and tidal waters from the federal registry and the $15.00 federal registration fee imposed in 2011. The Department of Environmental Protection (DEP) implemented the New Jersey Saltwater Recreational Registry Program (NJSRRP) effective May 4, 2011 through Administrative Order No. 2011-05 . Who Needs to Register? NOTE: Anglers with a valid registration with the National Saltwater Angler Registry or have a valid license from another exempted state are required to register (for free) with the NJ Saltwater Recreational Registry Program. Registration with NJ will exempt you from having to register with the National Saltwater Angler Registry. Individual saltwater anglers ages 16 and older MUST register if ANY of the following criteria are met: - Recreationally fish with a hand line or rod and line, spearfish or fish by hand - Recreationally fish in the marine and fresh tidal waters of the State of New Jersey - Recreationally fish in marine waters outside the State of New Jersey but land the catch in New Jersey Individual saltwater anglers are EXEMPT from registering if either of the following apply: - Under the age of 16 - Solely fish on for-hire (party and charter) vessels that are registered with the New Jersey Saltwater Recreational Registry Program For-hire vessel owners/operators MUST register if: - Carry individuals who engage in recreational fishing in the marine and fresh tidal waters of the State of New Jersey OR - Carry individuals who engage in recreational fishing in the marine waters outside the State of New Jersey but land their catch in New Jersey From chat GPT: In New Jersey, specific businesses require a Saltwater Angler registration to legally engage in saltwater fishing activities. These businesses include: 1. Charter Boats and Party Boats: Companies offering chartered fishing trips or party boat services where patrons pay to fish in New Jersey's marine and estuarine waters. 2. Tackle Shops: Retailers that sell fishing equipment and may provide guidance or services related to saltwater fishing. 3. Marinas: Facilities that offer boat docking, storage, and other services for recreational fishing vessels. 4. Fishing Guides: Professional guides who lead fishing expeditions for clients in saltwater areas. These businesses are required to register with the New Jersey Saltwater Recreational Registry Program to ensure they comply with state regulations and contribute to the management and conservation of marine resources. The registration helps the state monitor fishing activities and maintain sustainable fish populations. | BQ14: Fish & Wildlife | BR14: https://dep.nj.gov/njfw/fishing/marine/saltwater-registry/ | BU14: Individual Registration | BV14: Data stored in another DEP-owned system
A15: Bus Equipment (Safety Inspection Certs.) | B15: Motor Vehicle Commission | C15: 89030 | D15: Yes this is a business/shop plurmit | E15: Not | F15: Yes - Mention but not Integrate | G15: Not integrated since it is not an application, you call to schedule the inspection | H15: Mentioned | S15: Combined data from 2018 and 2021 | T15: No link | V15: SS-14 - CMC-12 -CMC12 | W15: N | X15: In person | Y15: In person | Z15: .Net or Java service or pdf acrobrat forms | AA15: $115(First recheck);$50(recheck);$70(recheck restoration) | AB15: $115(First recheck);$50(recheck);$70(recheck restoration) | AC15: Yes | AE15: No | AG15: No | AI15: Customer gets sticker.
A16: Individual and Business Major Line Renewal | B16: Department of Banking and Insurance | C16: 85930 | D16: Yes this is a business/shop plurmit | E16: Submitted | F16: No | G16: the renewal dates are automatically assigned and can vary depending on the users birthday month. This means we would need an integration in order to do this and have the correct expiration date | H16: No | S16: Combined data from 2018 and 2021 | U16: nipr.com | W16: Y | X16: Online | Y16: Mail,Online | AC16: No | AE16: No | AG16: No | AI16: INS
A17: Single Trip Permit (5 day) | B17: Department of Transportation | C17: 82341 | D17: Yes businesses often apply for this plurmit (for a device or project or something else) | E17: Submitted | F17: Yes - Mention but not Integrate | G17: Need further discussions on data partnership with agency before integration | H17: Mentioned | I17: https://dev.account.business.nj.gov/mgmt/cms#/collections/anytime-action-tasks-licenses/entries/single-trip-osow-permit | S17: Combined data from 2018 and 2021 | T17: https://nj.gotpermits.com | U17: https://nj.gotpermits.com | W17: Y | X17: Online | Y17: Online | Z17: Bentley Systems | AA17: $25.00 - $2000+ | AB17: $25.00 - $2000+ | AC17: Yes | AE17: No | AF17: Current online permit program available | AG17: Yes | AI17: Varies by size and weight
A18: Appointment Renewal (electronic only) | B18: Department of Banking and Insurance | C18: 78670 | D18: Yes, but primarily used by large businesses | E18: Submitted | F18: No | G18: out of scope for BizX, this is focused on large insurance companies | H18: No | S18: Combined data from 2018 and 2021 | T18: www.nipr.com | U18: https://pdb.nipr.com/ren/renUseAgree.jsp | W18: Y | X18: Online | Y18: Online | AC18: No | AE18: No | AG18: No | AI18: INS
A19: NJ Partnership Tax Extension to file NJ-CBT-1065 | B19: Department of the Treasury | C19: 75755 | D19: Yes this is a business/shop plurmit | F19: Yes - High Priority Integration | H19: Read | I19: https://dev.account.business.nj.gov/mgmt/cms#/collections/filings/entries/cbt-206 | R19: Division of Taxation | S19: 2021 Permit List | T19: https://nj.gov/treasury/taxation/prntpart.shtml | U19: https://www1.state.nj.us/TYTR_BusinessFilings/jsp/common/Login.jsp?taxcode=43 | V19: CBT-206 | X19: Online | Y19: In Person,Online,Mail | Z19: DORES Web Portal & AXWAY (3rd party software vendor) | AI19: Partnerships that are members of an entity electing to pay the Pass-Through Business Alternative Income Tax and that choose to apply the credit for their share of the tax to their nonresident partners tax must claim the credit on the NJ-CBT-1065. | AJ19: Yes | AK19: Cannot provide rejection counts due to daily changes. | AL19: Instantaneous | AM19: Yes | AN19: No | AO19: Yes | AQ19: Yes | AR19: Yes | AS19: No | AT19: Registration, Data Integrity, Calculation | AU19: 2019 | AV19: No | BH19: Yes | BK19: RL
A20: Boiler Inspection Certificates | B20: Department of Labor and Workforce Development | C20: 72794 | D20: Yes this is a business/shop plurmit | E20: Not | F20: Yes - Mention but not Integrate | G20: This will not be an integration, only a mention | H20: Mentioned | S20: Combined data from 2018 and 2021 | Y20: Mail,Email | AA20: Varies | AB20: Varies | AC20: Yes | AE20: No | AG20: No | AI20: https://www.nj.gov/labor/safetyandhealth/programs-services/boiler-pressure-vessel-compliance/ | BH20: Yes | BK20: RL | BL20: Get Your Boiler Registered and Inspected
A21: Vehicle Tile/Registration | B21: Motor Vehicle Commission | C21: 66018 | D21: Yes businesses often apply for this plurmit (for a device or project or something else) | E21: Not | F21: Yes - High Priority Integration | G21: Mentioned, integration in progress | H21: Mentioned
A22: Initial Resident & Nonresident Individual (Major Lines) | B22: Department of Banking and Insurance | C22: 62381 | D22: Yes this is a business/shop plurmit | E22: Submitted | F22: Yes - Mention but not Integrate | H22: Mentioned | S22: Combined data from 2018 and 2021 | T22: www.nipr.com | U22: nipr.com | W22: Y | X22: Online | Y22: Mail,Online | AC22: No | AE22: No | AG22: No | AI22: INS
A23: Emergency Trip Permit | B23: Division of Alcohol Division Control | C23: 60000 | D23: Yes this is a business/shop plurmit | F23: Yes - High Priority Integration | G23: The integration was added to account.Business.NJ.gov on 7/21/2025. This integration allows the user to enter the relevant data points in account.Businss.NJ.gov and to then submit the form which results in the data being sent via API to NICUSA (i.e. Tyler Technology) which consumes the data and returns the Permit for the user. | H23: Read and/or Write | J23: ADO 7863, ADO 14467, ADO 14936, ADO 15167, ADO 15204 | N23: Y | O23: Transportation and Warehousing | Q23: Y | U23: https://dev.account.business.nj.gov/actions/emergency-trip-permit | AA23: 30 | AB23: 30 | AH23: https://nj.accessgov.com/abc/Forms/Page/abc/emergencytrippermitshelp/0 | AI23: The integration was added to account.Business.NJ.gov on 7/21/2025. This integration allows the user to enter the relevant data points in account.Businss.NJ.gov and to then submit the form which results in the data being sent via API to NICUSA (i.e. Tyler Technology) which consumes the data and returns the Permit for the user. | BO23: Transportation and Warehousing | BT23: transportation
A24: Address Change | B24: Department of Banking and Insurance | C24: 58892 | E24: Submitted | F24: Unsure/need clarification | G24: need to align with SME | H24: No | S24: Combined data from 2018 and 2021 | W24: Y | X24: Online | Y24: Online | AA24: 50 | AB24: 50 | AC24: Yes | AE24: No | AG24: No | AI24: REC/Insurance
A25: CDL (Commercial Driver's License) | B25: Motor Vehicle Commission | C25: 53000 | D25: Yes businesses often apply for this plurmit (for a device or project or something else) | E25: Not | F25: Yes - High Priority Integration | G25: UX work done, needs to be implemented by dev. Potential to integrate | H25: No | K25: Evergreen
A26: International Registration Plan (IRP) | B26: Motor Vehicle Commission | C26: 52793 | D26: Yes businesses often apply for this plurmit (for a device or project or something else) | E26: Submitted | F26: Yes - Mention but not Integrate | G26: Need to discuss with SME if integration is possible | H26: Mentioned | S26: Combined data from 2018 and 2021 | T26: https://www.state.nj.us/mvc/pdf/commercial/irpqui1.pdf | V26: IRP-7/MCS-Irp-1,MCS-IRP-2 | W26: Y | X26: Mail,Online | Y26: Online | Z26: .Net or Java service or pdf acrobrat forms | AA26: Varies according to size and weight of vehicle | AB26: Varies according to size and weight of vehicle | AC26: Yes | AE26: No | AG26: No
A27: Salesperson - Renewal (2021-2023) | B27: Department of Banking and Insurance | C27: 49142 | D27: No, this is for municipalities or residents but not businesses | F27: No | H27: No | S27: 2021 Permit List | U27: https://www-dobi.state.nj.us/DOBI_RELOLSRV/LicenseeLogin | X27: Online | Y27: Mail | Z27: NJDOBI website | AA27: 301 | AJ27: 0 | AK27: 10 | AL27: 30 | AM27: 1 | AN27: 0 | AO27: 1 | AP27: 4 | AQ27: No | AR27: 1 | AS27: No | AT27: Non CE compliant | AV27: Yes
A28: New Jersey Partnership Return Corporation Business Tax | B28: Department of the Treasury | C28: 44811 | D28: Yes this is a business/shop plurmit | F28: High Priority Integration, lacking agency buy-in | H28: Read | I28: https://dev.account.business.nj.gov/mgmt/cms#/collections/filings/entries/nj-1065 | R28: Division of Taxation | S28: 2021 Permit List | T28: https://nj.gov/treasury/taxation/prntpart.shtml | U28: https://www1.state.nj.us/TYTR_BusinessFilings/jsp/common/Login.jsp?taxcode=43 | V28: NJ-CBT-1065 | X28: Online | Y28: In Person,Online,Mail | Z28: DORES Web Portal & AXWAY (3rd party software vendor) | AJ28: Yes | AK28: Cannot provide rejection counts due to daily changes. | AL28: Instantaneous | AM28: Yes | AN28: No | AO28: Yes | AQ28: Yes | AR28: Yes | AS28: No | AT28: Registration, Data Integrity, Calculation | AU28: 2019 | AV28: No | BH28: Yes | BK28: RL
A29: Pressure Vessel Inspection Certificates (includes refrigeration) | B29: Department of Labor and Workforce Development | C29: 43637 | D29: Yes this is a business/shop plurmit | E29: Not | F29: Yes - Mention but not Integrate | H29: Mentioned | S29: Combined data from 2018 and 2021 | Y29: Mail,Email | AA29: Varies | AB29: Varies | AC29: Yes | AE29: No | AG29: No | AI29: In New Jersey, the Bureau of Boiler and Pressure Vessel Compliance (BB&PVC) requires that pressure vessels, boilers, and refrigeration equipment be inspected at regular intervals https://www.nj.gov/labor/safetyandhealth/assets/PDFs/Boiler%20and%20Pressure%20Vessel%20Compliance/bbpvc_infoguide.pdf | BH29: Yes | BK29: RL
A30: Home Improvement Contractor (Renewal) | B30: Department of Law and Public Safety | C30: 42689 | D30: Yes this is a business/shop plurmit | F30: Yes - High Priority Integration | H30: Read | K30: Evergreen | R30: Division of Consumer Affairs | AI30: Renewal submission volume is an average of 2020-2024 | BD30: https://dev.account.business.nj.gov/mgmt/cms#/collections/license-calendar-events/entries/home-contractor | BH30: Yes | BL30: Home Improvement Contractor Renewal Deadline
A31: Employer Payroll Tax | B31: Department of the Treasury | C31: 42665 | D31: Yes this is a business/shop plurmit | F31: High Priority Integration, lacking agency buy-in | H31: Read | I31: https://dev.account.business.nj.gov/mgmt/cms#/collections/filings/entries/nj-927-h | R31: Division of Taxation | S31: 2021 Permit List | U31: https://www1.state.nj.us/TYTR_BusinessFilings/jsp/common/Login.jsp?taxcode=45 | V31: NJ927H | X31: Online | Y31: Online | Z31: DORES Web Portal & AXWAY (3rd party software vendor) | AJ31: Yes | AK31: Cannot provide rejection counts due to daily changes. | AL31: Instantaneous | AM31: Yes | AN31: No | AO31: Yes | AP31: DORES | AQ31: Yes | AR31: Yes | AS31: No | AT31: Registration, Data Integrity, Calculation | AU31: 2020 | AV31: No | BH31: Yes | BK31: RL
A32: Streamlined Sales Tax | B32: Department of the Treasury | C32: 42560 | D32: Yes this is a business/shop plurmit | F32: High Priority Integration, lacking agency buy-in | G32: Mentioned on the register for taxes page on 9/18/2025 | H32: Mentioned | R32: Division of Taxation | S32: 2021 Permit List | U32: https://www2-tre.mwg.state.nj.us/TYTR_SSTP_WS/EFileService.asmx | V32: SST-50 | Y32: Online | Z32: SST Web Services Portal | AI32: https://www.streamlinedsalestax.org/Shared-Pages/faqs/faqs---about-streamlined | AJ32: Yes | AK32: Cannot provide rejection counts due to daily changes. | AL32: Instantaneous | AM32: Yes | AN32: No | AO32: Yes | AP32: DORES | AQ32: Yes | AR32: Yes | AS32: No | AT32: Registration, Data Integrity, Calculation | AU32: 2020 | AV32: No | BH32: Yes | BK32: RL
A33: Registered Representative-Agent (Bureau of Securities) | B33: Department of Law and Public Safety | C33: 38000 | D33: Yes, but primarily used by large businesses | E33: Submitted | F33: No | G33: Not pursuing this as it's for larger businesses, confirmed w Dillon | H33: No | S33: Combined data from 2018 and 2021 | T33: http://www.finra.org/file/form-u4-uniform-application-securities-industry-registration-or-transfer | U33: https://crd.finra.org | V33: Form U4 | W33: Y | X33: Online | Y33: Online | Z33: FINRA Web CRD (Central Registration Depository) | AA33: 60 | AB33: 60 | AC33: Yes | AD33: FINRA | AE33: Yes | AG33: No | AI33: may be technically individual: "an individual who is licensed to sell securities and has the legal power of an agent in the United States." - Wikipedia | BH33: Yes | BK33: RL
A34: Urban Enterprise Zone Sales Tax | B34: Department of the Treasury | C34: 37350 | D34: Yes this is a business/shop plurmit | F34: High Priority Integration, lacking agency buy-in | H34: Read | I34: https://dev.account.business.nj.gov/mgmt/cms#/collections/filings/entries/uz-50 | R34: Division of Taxation | S34: 2021 Permit List | U34: https://www1.state.nj.us/TYTR_BusinessFilings/jsp/common/Login.jsp?taxcode=11 | V34: UZ-50; UZ-50B | X34: Online | Y34: Online | Z34: DORES Web Portal | AJ34: Yes | AK34: Cannot provide rejection counts due to daily changes. | AL34: Instantaneous | AM34: Yes | AN34: No | AO34: Yes | AP34: DORES | AQ34: Yes | AR34: Yes | AS34: No | AT34: Registration, Data Integrity, Calculation | AU34: 2020 | AV34: No | BH34: Yes | BK34: RL
A35: Notary Public | B35: Department of the Treasury | C35: 32000 | D35: No, but certain employees need this license, and businesses might want to be aware of that/look up* | E35: Submitted | F35: Yes - Mention but not Integrate | H35: Mentioned | R35: Division of Revenue and Enterprise Services | S35: Combined data from 2018 and 2021 | T35: nj.gov/njbgs | U35: nj.gov/njbgs | W35: Y | X35: Online | Y35: Online | Z35: NICUSA | AA35: 50 | AB35: 50 | AC35: Yes | AE35: No | AG35: No | BH35: Yes | BK35: RL | BL35: Register as a Notary Public
A36: Drinking Water (eDWR) | B36: Department of Environmental Protection | C36: 29458 | D36: No, this is for municipalities or residents but not businesses | E36: Submitted | F36: No | G36: Based on NJ A.C. 7:10-5.4 requirements: - The submission of Drinking Water reports is primarily the responsibility of municipal water supply systems. - The submission of this type of report could be leveraged by a business that may not be connected to the local water supply and constructed/connected to an on-site well system, which mainly impacts rural-based businesses in NJ. - It seems like a super niche scenario that can span across all industries that are constructing a facility (not home-based) and operation that would provide drinking water to employees or customers. From Mike Matsko (DEP DataMiner App Owner) "Regarding the Ask, all drinking water data is made available in a separate application called Drinking Water Watch - There are some drinking water reports on DataMiner but none that show the monitoring results. - My understanding is that only Water Systems that provide water to the public report this data. If they don't submit they are issued a violation." Summary of Drinking Water Act - Both locations have active wells - Corbin Cafe Drinking Water Report & Hot Dog Johnnys Drinking Water Report Richard.Gunosky@dep.nj.gov is DWR Data POC in DEP Export of Drinking Water Watch - Systems across NJ Prioritization Rationale: We should focus on this later: - The possibility of a small-to-medium-sized business coming through B.NJ.gov + on a well and serving employees/customers is not a large pool. SBAB stated that many new businesses are located where they would connect to municipal water systems. - The majority of DWR submissions are coming from the larger entities (city/town water systems) since they must report DWR reports monthly. County Environmental Health Assoc. (PWSID) --> will require facilities to report their water quality reports | H36: N/A | S36: Combined data from 2018 and 2021 | T36: https://www.nj.gov/dep/online/ | U36: https://www.nj.gov/dep/online/ | X36: Online | Y36: Online | Z36: DEP Online | AC36: No | AE36: No | AG36: No | AH36: https://www.nj.gov/dep/online/ | BP36: From DEP User Guide: The New Jersey Electronic Environmental Reporting System (E2) is a web-based information system that allows the regulated community to electronically submit reports to the Department of Environmental Protection (NJDEP). - The E2 system provides an alternative to submitting hand-written or paper-based reports that is faster, more efficient, and requires less processing for water systems and the NJDEP. - As a fully operational electronic reporting system, all of the necessary legal, security, and electronic signature functionalities have been included to serve as a completely paperless reporting system. Currently, the E2 system allows laboratories to submit three major categories of reports: - Electronic Drinking Water Reports (DWR) - Electronic New Jersey Quantitation Limit (NJQL) reports - Electronic Private Well Testing Act (PWTA) Reports Currently, the E2 system allows water systems to perform the following major functions: - View Electronic Drinking Water Reports (DWR) containing analytical results submitted by laboratories on behalf of water systems - Submit the Annual Water Utilization report The Bureau of Safe Drinking Water has not made all forms available for electronic submission. Therefore, a water system may need to submit Drinking Water data electronically for some reports and use paper for other reports. | BQ36: Water Supply | BR36: https://www.nj.gov/dep/online/e2/NJ_E2_v1.3_DWR_Users_Guide.pdf | BT36: health-club,restaurant,daycare,lodging | BU36: Report/Logbook | BV36: Data stored in another DEP-owned system | BW36: My business will have its own well for water supply that has at least 15 service connections. ,My business regularly serves an average of at least 25 individuals daily for at least 60 days out of the year. ,My business will be drilling wells.
A37: Drinking Water Reports (DWR) | B37: Department of Environmental Protection | C37: 29456 | D37: No | E37: Submitted | F37: No | G37: Based on NJ A.C. 7:10-5.4 requirements: - The submission of Drinking Water reports is primarily the responsibility of municipal water supply systems. - The submission of this type of report could be leveraged by a business that may not be connected to the local water supply and constructed/connected to an on-site well system; which mainly impacts rural-based businesses in NJ. - It seems like a super niche scenario that can span across all industries that are constructing a facility (not home-based) and operation that would provide drinking water to employees or customers. From Mike Matsko (DEP DataMiner App Owner) "Regarding the Ask, all drinking water data is made available in a separate application called Drinking Water Watch - There are some drinking water reports on DataMiner but none that show the monitoring results. - My understanding is that only Water Systems that provide water to the public report this data. If they don't submit they are issued a violation." Summary of Drinking Water Act - Both locations have active wells - Corbin Cafe Drinking Water Report & Hot Dog Johnnys Drinking Water Report Richard.Gunosky@dep.nj.gov is DWR Data POC in DEP Export of Drinking Water Watch - Systems across NJ | H37: N/A | S37: Combined data from 2018 and 2021 | T37: www.njdeponline.com | X37: Online | Y37: Online | Z37: Regulatory Service Portal (njdeponline) | AC37: No | AE37: No | AG37: No | AH37: Guidance documents provided when requested | BP37: Based on a call with the Water Supply Director, this is a dupe record from the data dump in 2018/2021. All E2 reports (DWRs) are submitted electronically | BQ37: Water Supply | BT37: health-club,restaurant | BU37: Report/Logbook | BV37: Data stored in another DEP-owned system
A38: Weights and Measures Device Registration Certification (Business) | B38: Department of Law and Public Safety | C38: 26609 | D38: Yes businesses often apply for this plurmit (for a device or project or something else) | E38: Available | F38: High Priority Integration, lacking agency buy-in | H38: Mentioned | S38: Combined data from 2018 and 2021 | T38: https://www.njconsumeraffairs.gov/OWM/Applications/Registration-Application-for-Commercial-Weighing-and-Measuring-Devices.pdf | W38: N | X38: In person,Mail,Online | Y38: In person,Mail | Z38: DCA Website | AA38: $- | AC38: No | AE38: No | AG38: No | BH38: Yes | BK38: RL | BL38: "weights-measures-registration - Register a Scale, Meter, or Other Weighing and Measuring Device for Your Business"
A39: Code 23 Oversize/Overweight Permit (30 day) | B39: Department of Transportation | C39: 23872 | D39: Yes businesses often apply for this plurmit (for a device or project or something else) | E39: Submitted | F39: Yes - Mention but not Integrate | G39: Need further discussions and data partnership with agency before integration | H39: Mentioned | I39: https://dev.account.business.nj.gov/mgmt/cms#/collections/anytime-action-tasks-licenses/entries/code23-osow-30day-permit_1?ref=workflow | S39: Combined data from 2018 and 2021 | T39: https://nj.gotpermits.com | U39: https://nj.gotpermits.com | W39: Y | X39: Online | Y39: Online | Z39: Bentley Systems | AA39: 12.6 | AB39: 12.6 | AC39: Yes | AE39: No | AF39: Current online permit program available | AG39: Yes
A40: Referral Agent - Renewal (2021-2023) | B40: Department of Banking and Insurance | C40: 23247 | D40: No, this is for municipalities or residents but not businesses | F40: No | H40: No | S40: 2021 Permit List | U40: https://www-dobi.state.nj.us/DOBI_RELOLSRV/LicenseeLogin | X40: Online | Y40: Online | Z40: NJDOBI website | AA40: 100 | AJ40: 0 | AK40: 0 | AL40: 30 | AM40: 1 | AN40: 0 | AO40: 1 | AP40: 4 | AQ40: No | AR40: 1 | AS40: No | AV40: Yes
A41: OPRA Requests | B41: Department of Environmental Protection | C41: 21290 | D41: No, this is for municipalities or residents but not businesses | E41: Submitted | F41: No | G41: Peter from DEP OIT shared that the lawyers or consultants of large businesses would submit OPRA requests to plan for site remediation and construction activities. DEP OIT also created DataMiner to reduce the amount of OPRA requests | H41: N/A | S41: Combined data from 2018 and 2021 | T41: https://www.nj.gov/dep/online/ | U41: https://www.nj.gov/dep/online/ | X41: Online | Y41: Online | Z41: DEP Online | AC41: No | AE41: No | AG41: No | AH41: https://www.nj.gov/dep/online/ | BP41: OPRA stands for the Open Public Records Act. OPRA requests are formal requests made by individuals or organizations to access government records held by public agencies in New Jersey. The NJDEP, as a state agency, is subject to OPRA and must provide access to its public records. This includes a wide array of documents related to environmental regulation, monitoring, enforcement, permits, site remediation, and other activities under the NJDEP's purview. | BR41: https://www.nj.gov/dep/opra/opraform.html | BU41: Records Request
A42: Pass-through Business Alternative Income Tax Return | B42: Department of the Treasury | C42: 20485 | D42: Yes this is a business/shop plurmit | F42: High Priority Integration, lacking agency buy-in | G42: An extension for filing PTE100 is also in the CMS (PTE200): https://dev.account.business.nj.gov/mgmt/cms#/collections/filings/entries/pte-200 | H42: Read | I42: https://dev.account.business.nj.gov/mgmt/cms#/collections/filings/entries/pte-100 | R42: Division of Taxation | S42: 2021 Permit List | T42: https://www.state.nj.us/treasury/taxation/pteforms.shtml | U42: https://www1.state.nj.us/TYTR_BusinessFilings/jsp/common/Login.jsp?taxcode=09 | V42: -PTE 100.00 | X42: Online | Y42: Online | Z42: DORES Web Portal & AXWAY (3rd party software vendor) | AI42: https://www.nj.gov/njbonds/treasury/taxation/baitpte/index.shtml | AJ42: Yes | AK42: Cannot provide rejection counts due to daily changes. | AL42: Instantaneous | AM42: Yes | AN42: No | AO42: Yes | AQ42: Yes | AR42: Yes | AS42: No | AT42: Registration, Data Integrity, Calculation | AU42: 2020 | AV42: No | BH42: Yes | BK42: RL
A43: NJPDES Monitoring Reports - DMRs | B43: Department of Environmental Protection | C43: 20087 | D43: No, this is for municipalities or residents but not businesses | E43: Submitted | F43: No | G43: Tl;dr -- applies to businesses, but the discharge limits for Business.NJ.gov personas of interest do not reach the thresholds for reporting requirements. Small-to-medium-sized businesses that might be required to submit an NJPDES Discharge Monitoring Report (DMR) include those in industries where they discharge wastewater or other pollutants into state waters or sewage treatment plants. Here are some examples: 1. Manufacturing Companies: Factories that produce goods like clothing, electronics, furniture, or machinery. 2. Food Processing Plants: Businesses that process food items, such as dairies, breweries, and meat processing plants. 3. Automotive Services: Auto repair shops, car washes, and detailing services. 4. Agricultural Operations: Farms that involve livestock or large-scale crop production. 5. Construction Companies: Businesses involved in building or renovating structures that may affect water runoff. 6. Chemical Plants: Small facilities producing or using chemicals for various products. 7. Metal Plating and Finishing: Companies that treat metals to create finished products. 8. Printing and Publishing: Businesses that use printing presses and other equipment that can discharge pollutants. 9. Textile Mills: Small factories producing fabrics or clothing. 10. Laundries and Dry Cleaners: Particularly those that handle large volumes of textiles. 11. Pharmaceuticals and Cosmetics: Small companies producing medicines, creams, and other products. 12. Woodworking and Furniture Making: Businesses that use wood treatment processes. 13. Bakeries and Confectioneries: Large-scale baking and candy production facilities. 14. Breweries and Wineries: Small breweries and wineries that produce alcoholic beverages. 15. Electronic Assembly Plants: Facilities that assemble electronic components. These businesses are required to submit DMRs to ensure they are managing their wastewater and other discharges according to environmental regulations, helping to protect water quality in New Jersey. Electronic Submission Process of DMR to NJDEP (page 31) Permittees now have the opportunity to submit MRF data electronically to NJDEP. The Electronic Discharge Interchange (EDI) system has been created to combine today’s web technology with spreadsheet software technology. The system is designed to closely mirror the existing manual operation. Upon creation of an ID and PIN (personal identification number) and then approval from NJDEP, a permittee may download NJPDES EDI electronic spreadsheets via the NJDEP online web portal at http://www.state.nj.us/dep/online/ for electronic data entry. When data entry is complete, the form is validated, locked, and uploaded to NJDEP via NJDEP’s online web portal. After uploading, NJDEP sends an e-mail message to the permittees designated responsible official advising that the form is ready to be certified. The responsible official then accesses the web portal, reviews the form, and certifies it using their PIN. Once the file is certified the system spreadsheet data migrates over to NJDEP’s NJEMS database. At this point, the form is considered postmarked complete. Electronic files are stored onsite for review by Compliance and Enforcement. SBAP/Ky Asral Perspective "So even though this is for businesses, the discharge monitoring reports for the most part, it really would be on the rare side that they would be new businesses, especially like the small businesses. Unlikely, unless they are for some reason they're very water intensive or they have to treat their pollution in the facility by treating the water and then releasing it. But again those are gonna be rare." "You have a higher potential for industrial facilities to be having a DMR." "For example, if a facility needs a DMR, there's no general permit for that." The active NJDPES permit list shows majority of permittee who would submit a DMR are: - City/township treatment plants - energy & petroleum - chemical & pharmaceutical - Marine & equipment - Energy Generation - Apartment complexes - R&D facilities - Airports - plants - Pipelines | H43: No | S43: Combined data from 2018 and 2021 | T43: https://www.nj.gov/dep/online/ | U43: https://www.nj.gov/dep/online/ | X43: Online | Y43: Online | Z43: DEP Online | AC43: No | AE43: No | AG43: No | AH43: https://www.nj.gov/dep/online/ | BP43: Think of the NJPDES Discharge Monitoring Report (DMR) as a report card for a factory or a business that releases water into the environment. Just like a report card shows how well a student is doing in school, the DMR shows how well the factory or business is doing in keeping the water they release clean. Here’s a simpler way to understand it: 1. Purpose: The main goal is to make sure the water that businesses and factories release into rivers, lakes, or the ground isn't too dirty or polluted. They have to follow certain rules to keep the water clean. 2. How It Works: Every so often, these businesses have to test the water they release. They check for different kinds of pollution, like chemicals or trash. Then, they write down the results in the DMR. 3. Why It’s Important: The DMR helps the state keep track of whether these businesses are following the rules. If they’re doing a good job, the water stays safe and clean for people, animals, and plants. If they’re not, they might get in trouble and have to fix the problem. 4. Consequences: If a business doesn't fill out the DMR correctly or tries to hide that they’re polluting too much, they can get fined (like a penalty) or even face more serious consequences. In short, the DMR is a way for the state to check that businesses are doing their part to keep the water clean and safe for everyone. -- ChatGPT 8th grade explanation | BQ43: Wastewater | BR43: https://dep.nj.gov/wp-content/uploads/dwq/mrf_manual-1.pdf | BT43: cannabis,breweries,agriculture (farms),Metal finishers,Food processors | BU43: Report/Logbook | BV43: Data stored in DEP Online/NJEMS
A44: Monthly Operators Report Form for Ground Water Systems (BSDW-40) | B44: Department of Environmental Protection | C44: 20000 | D44: No, this is for municipalities or residents but not businesses | E44: Available | F44: No | G44: Detailed Explanation here TL;dr -- Community water systems (town, cities) treating water at plants would be the submitter of the BSDW-40 | H44: N/A | S44: Combined data from 2018 and 2021 | T44: https://www.state.nj.us/dep/watersupply/xls/bsdw40.xls | X44: Online | Y44: Mail,Email | Z44: DEP Website | AC44: No | AE44: No | AG44: No | BP44: The purpose of this form is to ensure that businesses using or distributing groundwater monitor water quality to meet regulatory standards, thereby supporting ecological sustainability and protecting public health. The Monthly Operating Report (BSDW-40 or 41) is used to maintain daily records of water pumpage, chemical quantities, and routine test results. This report is submitted monthly by the 10th day of the month following the month for which the records contained in the report are compiled in accordance with N.J.A.C. 7:10A-1.12(d). | BQ44: Water Supply | BU44: Report/Logbook | BV44: No datastore for this PLURmit
A45: Multiple Dwellings Registration | B45: Department of Community Affairs | C45: 20000 | D45: Yes this is a business/shop plurmit | F45: High Priority Integration, lacking agency buy-in | H45: Read | K45: My Account Roadmap: Live | M45: Y | N45: Y | Q45: Y | R45: Codes and Standards (Bureau of Housing Inspection) | S45: http://www.nj.gov/dca/codes/offices/housinginspection.shtml | T45: https://njdcaportal.dynamics365portals.us/ | BN45: Real Estate Investing,Residential Landlord | BO45: Real Estate and Leasing
A46: Preserve Daily Stocking Record (pdf,34kb) | B46: Department of Environmental Protection | C46: 20000 | D46: No, this is for municipalities or residents but not businesses | E46: Available | F46: No | G46: Action tied to a PLURmit, does not enable the business to start or maintain operations | H46: N/A | S46: Combined data from 2018 and 2021 | T46: https://www.njfishandwildlife.com/pdf/daily_stocking_record.pdf | X46: Online | Y46: In person,Mail,Email | Z46: DEP Website | AC46: No | AE46: No | AG46: No | BP46: For semi-wild and commercial shooting preserves. These preserves are licensed to operate and manage the hunting of specific game birds like pheasants, quails, and partridges. Preserve operators need to keep accurate records of the game birds released within their preserves to ensure compliance with state regulations and for wildlife management purposes. More info at this website. This document seems to be used by hunting preserves for the purpose of quantifying stocked game birds on the preserve. It includes the species, gender, and quantity. NOTE: it's unclear by the title of this form whether the original document was for fisheries or commercial hunting preserves. "Stocking" is usually used for the former, such as commercial fisheries, fishing preserves, and hatcheries. The purposes of a Stocking document and its basic content are consistent, however, for both industries. Commercial Shooting Preserve Main Site | BQ46: Fish & Wildlife | BR46: https://dep.nj.gov/wp-content/uploads/njfw/daily_stocking_record.pdf | BT46: Commercial Shooting Preserves | BU46: Report/Logbook | BV46: No datastore for this PLURmit
A47: Landlord Registration | B47: Department of Community Affairs | C47: 20000 | D47: Yes the shop owner needs this individual plurmit | F47: High Priority Integration, lacking agency buy-in | H47: Mentioned | K47: My Account Roadmap: Planned Anytime Action: ? | L47: Y | M47: Y | N47: Y | P47: Y | R47: Codes and Standards (but file on local level) | BN47: Residential Landlord | BO47: Real Estate and Leasing
A48: Preserve Daily Kill Sheet (pdf,5kb) | B48: Department of Environmental Protection | C48: 20000 | D48: No, this is for municipalities or residents but not businesses | E48: Available | F48: No | G48: This is a record-keeping document – not a permit or license – that exists for only one industry: commercial shooting preserves. There are over 358k acres of hunting land in the state, but I can't find a specific number of commercial hunting grounds. The log sheet is paper-based, and there is no information on NJDEP on where to submit it or keep it as a back office doc in case an inspector comes by. | H48: N/A | S48: Combined data from 2018 and 2021 | T48: https://www.njfishandwildlife.com/pdf/daily_kill_sheet.pdf | X48: Online | Y48: In person,Mail,Email | Z48: DEP Website | AC48: No | AE48: No | AG48: No | BP48: For semi-wild and commercial shooting preserves. These preserves are licensed to operate and manage the hunting of specific game birds like pheasants, quails, and partridges. Preserve operators need to keep accurate records of the game birds harvested within their preserves to ensure compliance with state regulations and for wildlife management purposes. More info at this website. The Kill Sheet requires operators to gather data on daily kills, noting the gender ("hen" or "cock") of the bird. This is for population management and regulation compliance purposes, as well as for data collection. Commercial Shooting Preserve Main Site | BQ48: Fish & Wildlife | BR48: https://www.nj.gov/dep/fgw/pdf/daily_kill_sheet.pdf | BT48: Commercial Shooting Preserves | BU48: Report/Logbook | BV48: No datastore for this PLURmit
A49: Hotel/Motel Occupancy | B49: Department of the Treasury | C49: 19100 | D49: Yes this is a business/shop plurmit | F49: High Priority Integration, lacking agency buy-in | H49: Read | I49: https://dev.account.business.nj.gov/mgmt/cms#/collections/filings/entries/hm-100 | R49: Division of Taxation | S49: 2021 Permit List | U49: https://www1.state.nj.us/TYTR_BusinessFilings/jsp/common/Login.jsp?taxcode=22 | V49: HM-100 | X49: Online | Y49: Online | Z49: DORES web portal | AI49: https://nj.gov/treasury/njombudsman/treasury/taxation/hotelfeeinfo.shtml is at both state and municipal level taxes | AJ49: Yes | AK49: Cannot provide rejection counts due to daily changes. | AL49: Instantaneous | AM49: Yes | AN49: No | AO49: Yes | AQ49: Yes | AR49: Yes | AS49: No | AT49: Registration, Data Integrity, Calculation | AU49: 2020 | AV49: No | BH49: Yes | BK49: RL
A50: Pass-through Business Alternative Income Estimated Payments | B50: Department of the Treasury | C50: 17488 | D50: Yes this is a business/shop plurmit | F50: Yes - Mention but not Integrate | H50: Read | I50: https://dev.account.business.nj.gov/mgmt/cms#/collections/filings/entries/pte-150 | R50: Division of Taxation | S50: 2021 Permit List | T50: https://www.state.nj.us/treasury/taxation/pteforms.shtml | U50: https://www1.state.nj.us/TYTR_BusinessFilings/jsp/common/Login.jsp?taxcode=09 | V50: -PTE 150.00 | X50: Online | Y50: Online | Z50: DORES Web Portal & AXWAY (3rd party software vendor) | AI50: https://www.nj.gov/njbonds/treasury/taxation/baitpte/index.shtml similar to above -- tax return | AJ50: Yes | AK50: Cannot provide rejection counts due to daily changes. | AL50: Instantaneous | AM50: Yes | AN50: No | AO50: Yes | AQ50: Yes | AR50: Yes | AS50: No | AT50: Registration, Data Integrity, Calculation | AU50: 2020 | AV50: No | BH50: Yes | BK50: RL
A51: Charitable Organizations | B51: Department of Law and Public Safety | C51: 17096 | D51: Yes this is a business/shop plurmit | E51: Submitted | F51: High Priority Integration, lacking agency buy-in | H51: Mentioned | S51: Combined data from 2018 and 2021 | U51: https://www.njconsumeraffairs.gov/charities/Pages/charities-registration-information.aspx | W51: Y | X51: Online | Y51: Online | Z51: Microsoft CRM | AA51: $30-$250 | AB51: $30-$250 | AC51: Yes | AE51: No | AG51: No | BH51: Yes | BK51: RL | BL51: "Register Your Charity, if Applicable"
A52: Tire | B52: Department of the Treasury | C52: 16405 | D52: Yes businesses often apply for this plurmit (for a device or project or something else) | F52: High Priority Integration, lacking agency buy-in | H52: Read | I52: https://dev.account.business.nj.gov/mgmt/cms#/collections/filings/entries/tir-100 | R52: Division of Taxation | S52: 2021 Permit List | T52: https://www.state.nj.us/treasury/taxation/pdf/other_forms/misc/tir100.pdf | U52: https://www1.state.nj.us/TYTR_BusinessFilings/jsp/common/Login.jsp?taxcode=83 | V52: TIR-100 | X52: Online | Y52: Online | Z52: DORES web portal | AI52: Seems to be for businesses that sell tires | AJ52: Yes | AK52: Cannot provide rejection counts due to daily changes. | AL52: Instantaneous | AM52: Yes | AN52: No | AO52: Yes | AQ52: Yes | AR52: Yes | AS52: No | AT52: Registration, Data Integrity, Calculation | AU52: 2020 | AV52: No | BH52: Yes | BK52: RL
A53: Tax Clearance Certificate | B53: Department of the Treasury | C53: 15982 | D53: Yes businesses often apply for this plurmit (for a device or project or something else) | F53: Yes - High Priority Integration | H53: Read | K53: Evergreen | BH53: Yes
A54: NJ Partnership Tax Extension to file NJ-1065 | B54: Department of the Treasury | C54: 15801 | D54: Yes this is a business/shop plurmit | F54: High Priority Integration, lacking agency buy-in | H54: Read | I54: https://dev.account.business.nj.gov/mgmt/cms#/collections/filings/entries/part-200-t | R54: Division of Taxation | S54: 2021 Permit List | T54: https://nj.gov/treasury/taxation/prntpart.shtml | U54: https://www1.state.nj.us/TYTR_BusinessFilings/jsp/common/Login.jsp?taxcode=43 | V54: PART-200T | X54: Online | Y54: In Person,Online,Mail | Z54: DORES Web Portal & AXWAY (3rd party software vendor) | AI54: https://nj.gov/treasury/unclaimed-property/treasury/taxation/pdf/current/part/1065part.pdf | AJ54: Yes | AK54: Cannot provide rejection counts due to daily changes. | AL54: Instantaneous | AM54: Yes | AN54: No | AO54: Yes | AQ54: Yes | AR54: Yes | AS54: No | AT54: Registration, Data Integrity, Calculation | AU54: 2019 | AV54: No | BH54: Yes | BK54: RL
A55: Tractor Trailer (Owner) | B55: Motor Vehicle Commission | C55: 14578 | D55: Yes this is a business/shop plurmit | E55: Available | F55: No | G55: Same process as vehicle registration which we have already mentioned | H55: No | S55: Combined data from 2018 and 2021 | V55: BA-49 | W55: Y | X55: Online | Y55: In person | Z55: .Net or Java service or pdf acrobrat forms | AA55: Initial Registration and Renewal fee varies according to size & weight | AB55: Initial Registration and Renewal fee varies according to size & weight | AC55: Yes | AE55: No | AG55: No
A56: Slot Machine Licenses | B56: Casino Control Commission | C56: 14094 | D56: Yes this is a business/shop plurmit | E56: Not | F56: High Priority Integration, lacking agency buy-in | G56: Casino Control Commission, not TLC, not mentioned yet | H56: No | R56: Casino Control Commission | S56: Combined data from 2018 and 2021 | W56: N | AC56: No | AE56: No | AG56: No | BH56: Yes | BK56: RL
A57: Raffle | B57: Department of Law and Public Safety | C57: 13000 | D57: Yes this is a business/shop plurmit | E57: Available | F57: Yes - High Priority Integration | G57: Unsure if this is high-priority integration but lacking agency buy-in? | H57: Mentioned | S57: Combined data from 2018 and 2021 | T57: https://www.njconsumeraffairs.gov/lgccc/Pages/applications.aspx | W57: N | X57: In person,Mail,Online | Y57: In person,Mail | Z57: DCA Website | AA57: $0-$20 for every $1000 in Prize Money | AB57: $0-$20 for every $1000 in Prize Money | AC57: Yes | AD57: Notary & Municipal Clerk | AE57: Yes | AF57: Requires Municipal Approval | AG57: Yes | BH57: Yes | BK57: RL | BL57: Apply for a Raffle or Bingo Game License for Your Nonprofit
A58: GIS Deliverables Requirements - Site Remediation | B58: Department of Environmental Protection | C58: 13000 | D58: Yes businesses often apply for this plurmit (for a device or project or something else) | E58: Available | F58: Unsure/need clarification | G58: Could be a dupe of srp_forms_re@dep.nj.gov: https://airtable.com/appF6gh5a3ddPxdYM/pagqjEXIePl6Zgo7l?hhyLC=reckJFnQ9gZDXHcWQ Potential UX: - If biz states --> I'm planning to renovate/do construction on site via Non-EQ -> display environmental assessment task (for certain industries - industrial)? - Potentially a anytime action - Or add to Determine Site Requirements for Your X Business | H58: No | S58: 2018 Permit List | T58: https://www.nj.gov/dep/srp/gis/adminstrative_requirements_for_gis_deliverables.pdf | X58: Email,Online | Y58: Email | Z58: DEP Website | AC58: No | AE58: No | AG58: No | AH58: https://www.nj.gov/dep/srp/gis/adminstrative_requirements_for_gis_deliverables.pdf | BP58: The GIS Deliverables Requirements document from the NJDEP outlines the administrative requirements for submitting GIS deliverables related to environmental remediation projects. It is specifically used within the NJDEP's Site Remediation Program and covers various submission types such as Classification Exception Areas (CEAs), Area of Concern (AOC), Deed Notices (DN), Currently Known Extent (CKE), Well Receptor Searches (WRS), and more. Key Points of the Document: 1. GIS Submission Requirements: The document details how to format and submit Geographic Information System (GIS) data related to environmental sites via email, ensuring that all submissions are consistent and meet NJDEP's spatial accuracy and data integrity standards. 2. Types of Submissions: It lists specific types of GIS submissions (e.g., CEAs, DNs, WRS) and provides instructions on how to name files, format subject lines in emails, and manage submissions that involve multiple GIS records. 3. Metadata and Accuracy: Submissions must include specific metadata and meet NJDEP’s minimum accuracy standards for GIS data, ensuring that all spatial data submitted for environmental remediation projects are precise and reliable. 4. File Types and Formats: It instructs users to submit GIS files in specific formats, such as shapefiles for ARC users or DWG files for CAD users. It also describes naming conventions for these files to avoid confusion, especially when multiple records exist for a single site. Applicable Businesses: Businesses involved in site remediation where hazardous materials were handled, disposed of, or potentially released (e.g., industrial facilities or businesses with underground storage tanks). Small businesses are likely to encounter this requirement during: - The purchase of previously contaminated properties. - Expansion into industrial zones or older properties with potential contamination histories. Relation to Starting or Operating a Business: - Applicability: This document is most relevant to businesses involved in environmental remediation, site development, or construction projects that impact or monitor environmental conditions. Small businesses may need to engage with these requirements if they are developing property on contaminated land or involved in site clean-up efforts. - GIS Deliverables in Site Remediation: If a business operates on a site that is undergoing environmental remediation or is impacted by groundwater contamination, they may need to submit GIS data as part of regulatory compliance, particularly if the site has institutional controls like CEAs (to manage contamination) or areas of environmental concern. - Impact on Operations: For businesses starting or operating in areas subject to environmental regulations, submitting GIS deliverables as per these NJDEP guidelines ensures compliance with state requirements, helping to avoid fines or delays in development. These submissions could be necessary during due diligence or environmental assessments, which are critical for businesses acquiring or developing land in New Jersey. Conclusion: The GIS Deliverables Requirements document primarily serves businesses engaged in environmental remediation or those working on projects that affect the environment. Understanding and complying with these requirements is crucial for businesses that need to submit spatial data to the NJDEP as part of their regulatory obligations. | BQ58: Site Remediation | BT58: construction,real-estate-investor,funeral-services,daycare | BU58: Questionnaire | BW58: My business will take over an existing business or a site where a business used to be.,My business will carry out property assessment work at the site,My business will carry out construction activities on a site affecting 0.25 or more acres of land ,My business will carry out site improvement in or near wetlands or flood hazard areas. This includes activities such as cutting down trees. ,My business is planning construction for over 1 acre of land.,"My business will have stormwater discharge related to industrial activity. This includes activities such as warehousing, trucking, and recycling.",My business is going to take over an existing business with an industrial stormwater permit.,My business will be drilling wells.
A59: Pay for a License - Pesticides | B59: Department of Environmental Protection | C59: 13000 | D59: Yes this is a business/shop plurmit | E59: Submitted | F59: Yes - Mention but not Integrate | G59: Meets the following criteria: - Commonly applies to a small to medium business - Spans across multiple roles within a business We have several industries that are likely to need pesticide permits: - Lawncare - Petcare - Landscape architecture Additional due diligence may be required to confirm the activity types related to the 13,000 pesticide license payments. Is it a combination of new licenses (for businesses and individuals) and renewals (for existing businesses and individuals)? | H59: Mentioned | J59: https://content.account.business.nj.gov/tasks/commercial-pest-applicator-license | S59: Combined data from 2018 and 2021 | T59: https://www.nj.gov/dep/online/ | U59: https://www.nj.gov/dep/online/ | X59: Online | Y59: Online | Z59: DEP Online | AC59: No | AE59: No | AG59: No | AH59: https://www.nj.gov/dep/online/ | BP59: Tl;dr -- the ability for a permittee or registrant to pay for the initial pesticide business license or renewal invoice that is mailed annually. This isn't one PLURmit, but multiple potential plurmits related to application, training, and distribution of pesticides. Industries that might need to apply for these licenses include: - Exterminators: Companies that provide pest control services for residential and commercial properties. - Landscapers: Businesses that apply pesticides as part of lawn care and maintenance. - Tree Services: Companies involved in tree health and pest management. - Aerial Applicators: Services that apply pesticides from aircraft. - Pet Groomers: Businesses that use pesticides for flea and tick treatments. - Agriculture The licenses include: - AB_License_Application _VPA-013: Application for a new Pesticide Applicator Business license. - DB_License_Application _VPA-014: Application for a new Pesticide Dealer Business license. - Recert_Course_Application _VPA-015: Apply to offer a continuing education course. - Pesticide_Trainer_Application _VPA-016: Apply to become a Certified Pesticide Trainer. Instructions included. - Reciprocal_License_Application _VPA-017: Apply for, and make amendments to, a Reciprocal Pesticide Applicator License. - Operator_License_Application _VPA-028: Application for a new Pesticide Operator license. - Insurance_Coverage_Verification _VPI-001: Insurance verification form for a Pesticide Applicator Business. - Affidavit_VPE-001 Category Training Affidavit for previously licensed Pesticide Applicators reapplying for certification exams. Upload this form to your account in the PACER portal - at https://pacer.rutgers.edu/ - Training_Verification_ - Form _VPE-002 Category Training Verification form for initial Pesticide Applicators. Upload this form to your account in the PACER portal - at https://pacer.rutgers.edu/ https://www.nj.gov/dep/enforcement/pcp/bpo.htm | BQ59: Pesticide | BR59: https://www9.state.nj.us/DEP_RSP/Orchestrate.do?initiate=true&orchestrationId=NJDEP-EL-PayInvoice&service_category_id=30&service_class_id=109 | BT59: Aerial Pesticide Applicators,Landscapers,agriculture (farms),Tree Services / Arborists,Exterminators,lawn-care,Pest Control | BU59: Payment | BV59: Data stored in DEP Online/NJEMS | BW59: Will your business be using pesticides or offering pesticide application services?
A60: Pass-through Business Alternative Income Extension of time to File | B60: Department of the Treasury | C60: 12981 | D60: Yes this is a business/shop plurmit | F60: Yes - Mention but not Integrate | H60: Read | I60: https://dev.account.business.nj.gov/mgmt/cms#/collections/filings/entries/pte-200 | R60: Division of Taxation | S60: 2021 Permit List | T60: https://www.state.nj.us/treasury/taxation/pteforms.shtml | U60: https://www1.state.nj.us/TYTR_BusinessFilings/jsp/common/Login.jsp?taxcode=09 | V60: PTE-200-T | X60: Online | Y60: Online | Z60: DORES Web Portal & AXWAY (3rd party software vendor) | AJ60: Yes | AK60: Cannot provide rejection counts due to daily changes. | AL60: Instantaneous | AM60: Yes | AN60: No | AO60: Yes | AQ60: Yes | AR60: Yes | AS60: No | AT60: Registration, Data Integrity, Calculation | AU60: 2020 | AV60: No | BH60: Yes | BK60: RL
A61: Regular New Well Permit | B61: Department of Environmental Protection | C61: 12235 | D61: Yes businesses use a 3rd party business to apply to this plurmit | E61: Submitted | F61: Yes - Mention but not Integrate | G61: If we were to create a well-driller industry, there could be a use case for the permit as an anytime action. After further research, it seems like before the well is created, the well driller and homeowner must submit a license to the DEP. I also found that the driller needs to submit this application before being able to work on wells. This is probably an area we could explore further and potentially create a whole experience around it. In the Product Overview Dashboard, there are currently 6 businesses formed with the Well Drilling NAICS code 237110. PLURmit Process: The Well Drilling Company submits on behalf of a client by navigating to DEP Online -> Approval is instant after successful payment -> Well permit is valid for 365 days, and the well must be constructed within that timeframe Use Case: It's a common interaction for a well-driller, but would replicating the submission experience in B.NJ.gov be additive in nature and/or bring value to the agency and user vs. just informing them of the DEP Online submission experience? - There's a Unique ID for a well permit, which may require access to a new DB table in NJEMS Applicability Determination Reasoning - If we were to create a well-driller industry, there could be a use case for the plurmit as an anytime action. - However, this artifact would not necessarily help the for-hire well driller start or maintain compliance/operation. - See correspondence here | H61: Mentioned | S61: Combined data from 2018 and 2021 | T61: https://www.nj.gov/dep/online/ | U61: https://www.nj.gov/dep/online/ | X61: Online | Y61: Online | Z61: DEP Online | AA61: $130.00 - $1,300.00 | AC61: Yes | AE61: No | AG61: No | AH61: https://www.nj.gov/dep/online/ | BP61: When a licensed well driller plans to drill a well for a client, they must submit a New Well Permit to DEP. A submitted permit is here | BQ61: Water Supply | BR61: https://drive.google.com/file/d/1riLBgpQz2dPcpq-6dkGZRFKSgQpVsCL0/view?usp=sharing | BT61: Well Drillers | BU61: Permit | BV61: Data stored in DEP Online/NJEMS | BW61: My business will be drilling wells.
A62: Well Record | B62: Department of Environmental Protection | C62: 11013 | D62: Yes businesses use a 3rd party business to apply to this plurmit | E62: Submitted | F62: Yes - Mention but not Integrate | G62: PLURmit Process: The Well Drilling Company/Driller submits on behalf of a client by navigating to DEP Online -> Inputs: existing permit number and post-construction details + certification Use Case: It's a common interaction for a well-driller, but would replicating the submission experience in B.NJ.gov be additive in nature and/or bring value to the agency and user vs. just informing them of the DEP Online submission experience? - There's a Unique ID for a well permit, which may require access to a new DB table in NJEMS - I think it's similar to the regular new well permit, where we would have to create a new industry for this to be relevant to us. Applicability Determination Reasoning - If we were to create a well-driller industry, there could be a use case for the plurmit as an anytime action. - However, this artifact would not necessarily help the for-hire well driller start or maintain compliance/operation. - See correspondence here | H62: Mentioned | S62: Combined data from 2018 and 2021 | T62: https://www.nj.gov/dep/online/ | U62: https://www.nj.gov/dep/online/ | X62: Online | Y62: Online | Z62: DEP Online | AA62: $130.00 - $1,300.00 | AC62: Yes | AE62: No | AG62: No | AH62: https://www.nj.gov/dep/online/ | BP62: A well record must be submitted by the well driller to the Bureau of Water Systems and Well Permitting. Unless prior written approval is obtained from the Bureau of Water Systems and Well Permitting the well record shall be submitted electronically through the New Jersey Department of Environmental Protection's Regulatory Services Portal Submit Well Record: within ninety (90) days after the well is completed.[N.J.A.C. 7:9D-1] GPT: Purpose The Department manages extensive records of well permits, records, and abandonment reports across the state. To help locate a specific well record, certain information must be provided. Required Information 1. Well Drilling Permit Number: Though often unavailable to property owners, this number is used for tracking. 2. Well Owner at Time of Installation/Abandonment: Contact the local tax assessor to identify previous property owners or the homebuilder if the current owner did not install the well. The permit is issued to the owner at the time of installation. 3. Year Well was Installed/Abandoned: Provide the approximate age if the exact date is unknown. 4. Lot and Block Numbers: Obtain current and historical lot and block numbers from the local tax assessor. 5. Address of Property: Include the street address, nearest intersection, municipality, and county. A map photocopy is helpful but not required for abandonment report searches. 6. Additional Well Information: Include details such as casing material, diameter, length, depth, and driller information, if available. 7. Well Search Fee: No fee for homeowners or well decommissioning requests. All other requests require a $10 fee per well, payable to the Treasurer, State of New Jersey. | BQ62: Water Supply | BR62: https://drive.google.com/file/d/1riLBgpQz2dPcpq-6dkGZRFKSgQpVsCL0/view?usp=sharing | BT62: Well Drillers | BU62: Report/Logbook | BV62: Data stored in DEP Online/NJEMS | BW62: My business will be drilling wells.
A63: Certified Public Accountant (Renewal) | B63: Department of Law and Public Safety | C63: 10919 | D63: Yes the shop owner needs this individual plurmit | F63: Yes - Mention but not Integrate | H63: Mentioned | K63: Evergreen | R63: Division of Consumer Affairs | AI63: Renewal submission volume is an average of 2020-2024 | BD63: https://dev.account.business.nj.gov/mgmt/cms#/collections/license-calendar-events/entries/certified-public-accountant_1 | BH63: Yes | BL63: Accountant License Renewal Deadline
A64: Private Well Testing Act (PWTA) Analytical Results | B64: Department of Environmental Protection | C64: 10605 | D64: No, this is for municipalities or residents but not businesses | E64: Submitted | F64: No | G64: Laboratories submit well water quality results to NJDEP Online and via paper to the landlord during property sale transactions or every 5 years for recertification We could find synergies with MUNI's work on the landlord industry or if we introduce laboratories as new industry Applicability Determination Reasoning - If we were to create a well-driller industry or link this to the landlord industry, there could be a use case for the plurmit as an anytime action. - However, this artifact would not necessarily help the for-hire well driller start or maintain compliance/operation. - See correspondence here | H64: N/A | S64: Combined data from 2018 and 2021 | T64: https://www.nj.gov/dep/online/ | U64: https://www.nj.gov/dep/online/ | X64: Online | Y64: Online | Z64: DEP Online | AC64: No | AE64: No | AG64: No | AH64: https://www.nj.gov/dep/online/ | BP64: The property owner has to submit the following forms by mail to DEP after working with laboratories to test their water samples. GPT Summary: Overview - New Jersey Private Well Testing Act (PWTA): Enacted in March 2001, effective from September 2002. - Purpose: Consumer information law requiring sellers/buyers of properties with potable wells to test untreated groundwater for up to 43 parameters before closing the title. Landlords must test every five years and provide results to tenants. - Submission: Test results are submitted to the NJ Department of Environmental Protection (NJDEP) and local health authorities. Testing and Regulation - Scope: Approximately 25% of wells in NJ have been tested under this Act. - Encouragement for Homeowners: Homeowners with private wells are encouraged to routinely test their wells. - Construction Regulation: NJDEP regulates private well construction, with initial testing for contaminants; post-construction regulation is managed by local health departments. Resources and Tools - Interactive Maps: Online maps summarize PWTA data to inform homeowners about potential risks. - Certified Laboratories: NJDEP certifies labs to conduct PWTA testing. Detailed instructions and resources for labs are provided, including the electronic data delivery system (E2/Compass) for submitting test results. Laboratory Participation - Registration Process: Labs must register, create user accounts, and obtain PINs for electronic submissions. - Required Forms: - E2-LAB-001 for laboratory registration. - E2-ESA-001 for electronic signature agreement. - E2-LAB-002 for inactivation requests. - Submission Requirements: Laboratories must follow specific guidelines for data submission, including GPS coordinate collection in New Jersey State Plane Coordinate System. Contact Information - NJDEP Office of Quality Assurance: Handles lab certification and can be contacted for assistance. - Useful Links: Various resources and forms are available online for labs to ensure compliance with the PWTA. Additional Information - Regulations: Detailed regulations governing the certification of laboratories and environmental measurements. - Support: Contact details for further assistance related to the PWTA and lab certification processes. Conclusion The document emphasizes the importance of regular well testing for property transactions and rental properties, provides detailed guidance for certified laboratories, and offers resources to help ensure compliance with the PWTA. | BQ64: Water Supply | BR64: https://dep.nj.gov/wp-content/uploads/privatewells/pwta-reporting-form-pfas.pdf | BT64: home-contractor,real-estate-investor,Property Management,Residential Landloard,real-estate-broker | BU64: Report/Logbook | BV64: Data stored in DEP Online/NJEMS
A65: Striped Bass Bonus Program applications | B65: Department of Environmental Protection | C65: 10000 | D65: No, this is for municipalities or residents but not businesses | E65: Available | F65: No | G65: This is specific to a registered fisherman, there isn't an immediate business use case. Additionally, the form requires the fisherman/business owner of a charter/party boat to enter their SSN. Storing/transmitting this type of PII would most likely go against Business.NJ.gov's existing data governance and privacy fabric. | H65: N/A | S65: Combined data from 2018 and 2021 | T65: https://www.njfishandwildlife.com/bonusbas.htm | X65: Online | Y65: Mail | Z65: DEP Website | AC65: No | AE65: No | AF65: Completed application must include a self-addressed stamped envelope so the physical SBBP permit (tag) can be Mailed to the applicant. | AG65: Yes | AH65: https://www.njfishandwildlife.com/bonusbas.htm | BP65: This allows anglers can keep one additional fish at 24 inches to less than 28 inches from May 15 through December 31, 2024, in addition to the allowed one fish 28″ to 31″. Anglers can apply for this program after registering for the NJ Saltwater Recreational Registry Program. Program description from GPT: This program allows anglers to apply for permits that enable them to catch an additional striped bass beyond the standard recreational limits. The page includes details on how to apply for the bonus permit, the regulations and requirements for participating in the program, and the reporting process for any fish caught under the permit. Additionally, it provides contact information for further assistance and emphasizes the importance of compliance with program rules. | BQ65: Fish & Wildlife | BR65: https://dep.nj.gov/njfw/fishing/marine/sbbp-application/ | BU65: Individual Registration
A66: Cigarettes, Cigar Distribution, Vending Machine, Manufacture, Representative | B66: Department of the Treasury | C66: 10000 | D66: Yes this is a business/shop plurmit | E66: Submitted | F66: Yes - Mention but not Integrate | H66: Mentioned | R66: Division of Revenue and Enterprise Services | S66: Combined data from 2018 and 2021 | T66: nj.gov/njbgs | U66: nj.gov/njbgs | W66: Y | X66: Online | Y66: Online | Z66: NICUSA | AA66: 50 | AB66: 50 | AC66: Yes | AE66: No | AG66: No | AI66: First time applicants use paper app (per jaime) | BH66: Yes | BK66: RL | BL66: Apply for Your Cigarette License
A67: Emergency Medical Technician | B67: Department of Health | C67: 10000 | E67: Submitted | S67: Combined data from 2018 and 2021 | U67: https://njems.njlincs.net/jsp/index.jsp | W67: Y | X67: Online | Y67: Online | AA67: 0 | AC67: No | AE67: No | AG67: No
A68: MVC EIN (Corp Code) | B68: Motor Vehicle Commission | C68: 10000 | D68: Yes this is a business/shop plurmit | E68: Not | F68: Yes - Mention but not Integrate | H68: Mentioned | U68: https://www.nj.gov/mvc/pdf/business/BA-8.pdf | V68: BA-8
A69: Boiler Plant Stationary & Refrigeration Engineer, and Boiler Operator Licenses (Renewal) | B69: Department of Labor and Workforce Development | C69: 9824 | D69: Unsure/Need clarification | E69: Submitted | F69: Unsure/need clarification | G69: This is for a renewal -- where is the initial license? need more research | H69: No | S69: Combined data from 2018 and 2021 | T69: https://www.nj.gov/labor/forms_pdfs/lsse/MI-228.pdf | U69: https://joportal.com/nj/Spa/Home | X69: Online,Mail,Phone | Y69: Email,Mail,Online | Z69: NICUSA | AA69: $40-$80 | AB69: $40-$80 | AC69: Yes | AE69: No | AG69: No | AI69: Individual license renewal to operate/ maintain stationary equipment (boilers, refrigeration systems, power plants). Businesses need to employ these ppl, could potentially start their own business doing this? | BH69: Yes | BK69: JmL
A70: Pay a Paper Invoice | B70: Department of Community Affairs | C70: 9752 | D70: No | E70: Submitted | F70: No | G70: This isn't a plurmit but an action | M70: Y but this is an action tied to a specific plurmit | Q70: ? | R70: Division of Fire Safety | S70: Combined data from 2018 and 2021 | T70: https://www.nj.gov/dca/divisions/codes/RIMS_online.html | X70: Online | Y70: Online | Z70: RIMS | AA70: No Fee | AC70: No | AD70: NJ DFS | AE70: Yes | AG70: No | AH70: https://www.nj.gov/dca/divisions/RIMSHELP/index.htm
A71: Milk Vending Machine/Store Milk Licenses | B71: Department of Agriculture | C71: 9593 | E71: Submitted | S71: Combined data from 2018 and 2021 | T71: https://www.nj.gov/agriculture/applic/forms/newstoremilklic.pdf | U71: https://www24.state.nj.us/AG_MktDryLic/welcome.do | W71: Y | X71: Online,Mail,Phone,In person | Y71: Online,Mail,In person | Z71: NJFARMS/Java/Hosted on OIT's Glassfish Shared Services | AA71: Annual Fees based on volume of milk and milk products sold: $30 - $120 | AB71: Annual Fees based on volume of milk and milk products sold: $30 - $120 | AC71: Yes | AE71: No | AG71: No
A72: IRP/IFTA Trip Permits | B72: Motor Vehicle Commission | C72: 9530 | D72: Yes this is a business/shop plurmit | E72: Available | F72: Yes - Mention but not Integrate | G72: Published to CMS, not in prod yet | H72: Mentioned | S72: Combined data from 2018 and 2021 | T72: https://www.state.nj.us/mvc/business/irpiftaprocess.htm | U72: Various vendor sites | V72: Third party vendor | W72: N | X72: Online,Phone | Y72: Mail | Z72: .Net or Java service or pdf acrobrat forms | AA72: $25; additional fee applies depending on the weight and size of the vehicle | AB72: $25; additional fee applies depending on the weight and size of the vehicle | AC72: Yes | AD72: Comdata Inc., JJ Keller & associate Inc., Trans./Mid america | AE72: Yes | AG72: No
A73: Homemaker - HHA | B73: Department of Law and Public Safety | C73: 8891 | D73: No, but certain employees need this license, and businesses might want to be aware of that/look up* | E73: Submitted | F73: No | G73: Homemakers work under the supervision of an RN, could mention here: https://dev.account.business.nj.gov/mgmt/cms#/collections/tasks/entries/healthcare-license | H73: No | S73: Combined data from 2018 and 2021 | U73: https://www.njconsumeraffairs.gov/Pages/onlinelicenses.aspx | W73: Y | X73: Online | Y73: Online | Z73: System Automation (SA) | AA73: 50 | AB73: 50 | AC73: Yes | AE73: No | AG73: No | AI73: 2024 Annual Submission Volume: 13,590; Individual license to provide personal care/assistance w daily living to patients, usually in their home. Homemaker works under supervision of an RN. Initial and renewal applications online | BH73: No | BK73: JmL
A74: Decommission Well | B74: Department of Environmental Protection | C74: 8883 | D74: Yes businesses use a 3rd party business to apply to this plurmit | E74: Submitted | F74: Yes - Mention but not Integrate | G74: We would have to create a well-driller industry for this to be relevant to us. Update: Additional research suggests that this artifact is a required step when the property owner requests a "for-hire" well driller to decommission their well. This artifact would not necessarily help the for-hire well driller start or maintain compliance/operation. If we were to create a well-driller industry, there could be a use case for the plurmit as an anytime action. | H74: Mentioned | S74: Combined data from 2018 and 2021 | T74: https://www.nj.gov/dep/online/ | U74: https://www.nj.gov/dep/online/ | X74: Online | Y74: Online | Z74: DEP Online | AA74: $130.00 - $1,300.00 | AC74: Yes | AE74: No | AG74: No | AH74: https://www.nj.gov/dep/online/ | BP74: There are four forms related to well decommissioning a well. - Well Decommissioning Report - Well Permit Cancellation Form - Blanket 2” Well Decommissioning Approval Form - Blanket 2” Well Decommissioning Cover Letter STEP 5: REPORTING The final step of well abandonment in NJ is to report the newly decommissioned well to the New Jersey Department of Environmental Protection. Your licensed team of drillers will handle all the paperwork to get your abandoned well approved. Are you ready to start the process of well abandonment in NJ? | BQ74: Water Supply | BT74: Well Drillers | BU74: Report/Logbook | BW74: My business will be drilling wells.,My business will have its own well for water supply that has at least 15 service connections. ,"Do you use any unapproved water sources (e.g., wells, rainwater systems) alongside your municipal water supply?",My business regularly serves an average of at least 25 individuals daily for at least 60 days out of the year.
A75: Disinfectant Residuals Reporting Form | B75: Department of Environmental Protection | C75: 8800 | D75: No, this is for municipalities or residents but not businesses | E75: Available | F75: No | H75: N/A | S75: Combined data from 2018 and 2021 | T75: https://www.state.nj.us/dep/watersupply/xls/bsdw25.xls | V75: BSDW-25 | X75: Online | Y75: Mail,Email | Z75: DEP Website | AC75: No | AE75: No | AG75: No | BP75: The Disinfectant Residual Form (BSDW-25) (DR Form) must be completed by any water system that adds a chemical disinfectant or delivers water that has been previously treated with a chemical disinfectant (other than chlorine dioxide). All surface water, ground water under the direct influence of surface water (GWUDI) and consecutive systems that purchase surface water or purchase GWUDI (Subpart H systems) must submit a copy of this form on a monthly basis to the Bureau of Safe Drinking Water (Bureau). From chat GPT: In New Jersey, the Disinfectant Residual Form (BSDW-25) must be submitted by public water systems. These systems are required to monitor and report disinfectant residuals in the distribution system to ensure compliance with the Safe Drinking Water Act and New Jersey's regulations. | BQ75: Water Supply | BU75: Report/Logbook
A76: Litter Control Fee | B76: Department of the Treasury | C76: 8752 | D76: Yes this is a business/shop plurmit | F76: Yes - High Priority Integration | G76: Exists in CMS https://dev.navigator.business.nj.gov/mgmt/cms#/collections/filings/entries/lf-5 | H76: Read | I76: https://dev.account.business.nj.gov/mgmt/cms#/collections/filings/entries/lf-5 | R76: Division of Taxation | S76: 2021 Permit List | T76: https://www.state.nj.us/treasury/taxation/pdf/other_forms/misc/20lf5.pdf | V76: LF-5 | X76: Online | Y76: Mail | AI76: Business tax NJ retailers, manufacturers, wholesalers, or distributors of litter-generating products (tobacco, beer, food, empty cans/glass bottles, etc) | AJ76: Yes | AK76: Cannot provide rejection counts due to daily changes. | AL76: 1-2 days | AM76: No | AN76: No | AO76: Yes | AP76: DORES | AQ76: Yes | AR76: Yes | AS76: No | AT76: Registration, Data Integrity, Calculation | AU76: 2020 | AV76: No | BE76: https://dev.navigator.business.nj.gov/mgmt/cms#/collections/filings/entries/lf-5 | BH76: Yes | BK76: JmL
A77: Mortgage Loan Originator Individual (Fee Only at Initial App) | B77: Department of Banking and Insurance | C77: 8346 | D77: No, this is for municipalities or residents but not businesses | E77: Submitted | H77: No | S77: Combined data from 2018 and 2021 | T77: https://mortgage.nationwidelicensingsystem.org/Pages/default.aspx | U77: Log-on Required: https://mortgage.nationwi delicensingsystem.org/Pages/default.aspx | V77: MU4 | W77: Y | X77: Online | Y77: Online | Z77: Nationwide Mortgage Licensing System | AA77: 150 | AB77: 150 | AC77: Yes | AE77: No | AG77: No | AI77: OCF- Licensing
A78: Registered Professional Nurse | B78: Department of Law and Public Safety | C78: 8236 | D78: No, but certain employees need this license, and businesses might want to be aware of that/look up* | E78: Submitted | F78: Yes - Mention but not Integrate | G78: Mentioned here: https://dev.account.business.nj.gov/mgmt/cms#/collections/tasks/entries/healthcare-license | H78: Mentioned | S78: Combined data from 2018 and 2021 | U78: https://www.njconsumeraffairs.gov/Pages/onlinelicenses.aspx | W78: Y | X78: Online | Y78: Online | Z78: System Automation (SA) | AA78: 80 | AB78: 80 | AC78: Yes | AE78: No | AG78: No | AI78: 2024 Annual Submission Volume: (Reg Prof Nurse Single State) 3,779 and (Reg Prof Nurse Multi State) 8,465; Individual license. Must be RN to own firm. Initial and renewal applications online | BH78: Unsure/Need clarification | BK78: JmL | BL78: healthcare-license - Ensure Your Staff is Licensed
A79: NJPDES Monitoring Reports - WCRs | B79: Department of Environmental Protection | C79: 8037 | D79: No, this is for municipalities or residents but not businesses | E79: Submitted | F79: No | G79: After scanning the Active NJPDES Permit list, you'll see dairy farms, marinas and food processing plants as businesses that could come through the front of Business.NJ.gov. However, the majority of permittees are: - Municipal water treatment plants - Refineries - Hotels - Power plants - Rec fields - Pharmaceutical With the majority of active permittees being large-scale entities and the discharge data points being submitted by consultant groups or labs, it may be best to keep the submission of these reports in DEP Online. | H79: No | S79: Combined data from 2018 and 2021 | T79: https://www.nj.gov/dep/online/ | U79: https://www.nj.gov/dep/online/ | X79: Online | Y79: Online | Z79: DEP Online | AC79: No | AE79: No | AG79: No | AH79: https://www.nj.gov/dep/online/ | BP79: System (NJPDES) Monitoring Reports specifically related to Waste Characterization Reports (WCRs). Here's an overview of what these entail: 1. NJPDES Overview: - The NJPDES is a state-level regulatory program that controls water pollution by regulating point sources that discharge pollutants into New Jersey's surface water and groundwater. - It is part of the broader National Pollutant Discharge Elimination System (NPDES) program established under the Clean Water Act and administered by the U.S. Environmental Protection Agency (EPA). 1. Monitoring Reports: - NJPDES permits require permittees (e.g., industrial facilities, municipal wastewater treatment plants) to regularly monitor their discharges to ensure compliance with established pollutant limits. - Monitoring reports must be submitted to the New Jersey Department of Environmental Protection (NJDEP) as part of permit conditions. 1. Waste Characterization Reports (WCRs): - WCRs are a specific type of monitoring report required under the NJPDES program. - These reports detail the characteristics of the waste being discharged, including information on the type and concentration of pollutants. - WCRs help the NJDEP assess whether the discharge meets the regulatory standards and permit conditions. 1. Contents of WCRs: - WCRs typically include data on various parameters such as biochemical oxygen demand (BOD), chemical oxygen demand (COD), total suspended solids (TSS), pH, temperature, nutrient levels (e.g., nitrogen, phosphorus), and specific toxic substances. - The reports may also include information on the volume of discharge, sampling methods, frequency of monitoring, and analytical techniques used. 1. Purpose and Importance: - WCRs are crucial for ensuring that discharges do not harm water quality, public health, or the environment. - They provide the NJDEP with essential data to monitor compliance, identify potential issues, and take enforcement actions if necessary. 1. Submission and Review: - Permittees must submit WCRs according to the schedule specified in their NJPDES permits, which can be monthly, quarterly, or annually. - The NJDEP reviews these reports to ensure compliance with permit limits and to detect any violations or anomalies that may require further investigation or corrective action. 1. Public Access and Transparency: - As with other NJPDES documents, WCRs are generally subject to public access under the Open Public Records Act (OPRA). - Interested parties can request these reports to understand the environmental performance of specific facilities and to participate in regulatory processes. In summary, NJPDES Monitoring Reports - WCRs are critical documents that provide detailed information on the characteristics of waste discharges from permitted facilities in New Jersey. They play a vital role in the state's efforts to protect water quality and ensure compliance with environmental regulations. | BQ79: Wastewater | BT79: agriculture (farms),Food processors | BU79: Report/Logbook | BV79: Data stored in DEP Online/NJEMS
A80: 1001 - Elementary School Teacher in Grades K - 6 | B80: Department of Education | C80: 8006 | S80: 2018 Permit List | T80: https://www20.state.nj.us/DOE_TCIS_ONLINEED/ | U80: https://www20.state.nj.us/DOE_TCIS_ONLINEED/ | V80: 1001 | W80: Y | X80: Online | Y80: Online | Z80: Agency Web App - Teachers Cert (TCIS) | AA80: $95 - $200 | AB80: $95 - $200 | AC80: Yes | AD80: Notary (Only supporting docs) | AE80: Yes | AG80: No | AI80: Based On FY 2017-18 Data
A81: Pesticide Aquatic Permit RAT Form | B81: Department of Environmental Protection | C81: 8000 | D81: Yes businesses often apply for this plurmit (for a device or project or something else) | F81: Yes - Mention but not Integrate | G81: Annual reporting requirement for license holders applying pesticides in an aquatic environment | H81: No | S81: 2021 Permit List | T81: https://www.nj.gov/dep/enforcement/pcp/bpo-permits.htm N/A | V81: BPO-03 | X81: Online | Y81: Mail,Email | Z81: DEP Website | AJ81: No | AK81: filled out form incorrectly | AL81: 100 days | AM81: No | AN81: No | AO81: Yes | AP81: 44198 | AQ81: Yes | AR81: Yes | AS81: No | AT81: Yes | AU81: Aug 2021 - Aug 2020 | AV81: No | BP81: Non-EQ: Do you apply pesticides in an aquatic environment? Part 4. Record of Actual Treatment Record of Actual Treatment Form (BPO-03) - Excel Record of Actual Treatment Form (BPO-06) - Excel Instructions for Form BPO-03 - pdf As an aquatic pesticide applicator/applicator business, you are required to maintain a record of application for each aquatic pesticide application you perform. The information requested on this form shall be submitted to the PCP Permits Unit at AQRATS@dep.nj.gov by December 31st of the actual treatment year. Your aquatic pesticide application records shall contain all information required on Form BPO-03 (Form BPO-06 for 24C sites). Your application records shall include, but are not limited to, the information you are required to maintain on the Record of Actual Treatment forms. | BQ81: Pesticide | BR81: https://www.nj.gov/dep/enforcement/pcp/bpo-aqpermit.htm#part5 | BT81: Aerial Pesticide Applicators,Landscapers,lawn-care,agriculture (farms),Exterminators,Tree Services / Arborists,Pest Control | BU81: Report/Logbook | BV81: No datastore for this PLURmit | BW81: Will you apply pesticides in an aquatic environment?,Will your business be using pesticides or offering pesticide application services?
A82: Mobile Healthcare Continuing Education Program Licensing | B82: Department of Health | C82: 8000 | E82: Not | S82: 2018 Permit List | W82: N | X82: Phone | Y82: Email | AA82: 0 | AC82: No | AE82: No | AG82: No
A83: Pay a Paper Invoice Service for AEC 19 for X-Ray Machine Source | B83: Department of Environmental Protection | C83: 8000 | D83: Yes businesses often apply for this plurmit (for a device or project or something else) | E83: Submitted | F83: Yes - Mention but not Integrate | H83: Read | S83: Combined data from 2018 and 2021 | T83: https://www.nj.gov/dep/online/ | U83: https://www.nj.gov/dep/online/ | X83: Online | Y83: Online | Z83: DEP Online | AC83: No | AE83: No | AG83: No | AH83: https://www.nj.gov/dep/online/ | BP83: NOTE: Registration renewals are mailed 60 to 90 days prior to your registration expiration date. You should pay your invoice prior to the due date in order for your facility status to remain active. If your facility status is expired, then your registration fees are past due, and further use of your x-ray machines is in violation with N.J.A.C. 7:28-3.12(g). You need to immediately remit payment of your fees to the Department to avoid potential enforcement action. 1. To Renew On-Line: - Please have your invoice on hand as it contains your invoice number. Without the invoice number you will not be able to complete the on-line payment process. If you do not have this information, please email our office. - Prior to paying your fees on-line, click here to run the "X-ray Machines registered at Facilities" report. This report will let you verify the number of units registered at your facility and the registration fee for each machine. - If you find any discrepancies on your facilities report, you CANNOT renew on-line at this time. You MUST call and inform the Bureau. - If you have stored or disposed of an x-ray machine, you must complete a disposition form and fax it to the Bureau prior to paying your registration fees on-line. - The Bureau will notify you when you can pay your invoice on-line - Follow the instructions given in the "Express Payment" screen. - Once you have completed the payment process the “Payment Confirmation” screen should be printed and retained as proof of payment of your registration fees. If a facility/business has an x-ray, the Bureau will generate and mail an invoice for the application fee and pro-rated annual fee after processing your registration request. | BQ83: Radiation | BR83: https://www.nj.gov/dep/rpp/reg/renewal_instr_fees.htm | BT83: healthcare,veterinary | BU83: Payment | BV83: Data stored in DEP Online/NJEMS | BW83: Will you be using x-ray machines for your business?
A84: Home Improvement Contractor (HIC) | B84: Department of Law and Public Safety | C84: 7748 | D84: Yes this is a business/shop plurmit | E84: Available | F84: Yes - High Priority Integration | G84: Exists in CMS https://dev.navigator.business.nj.gov/mgmt/cms#/collections/license-tasks/entries/register-home-contractor | H84: Read | R84: Division of Consumer Affairs | S84: Combined Data from 2018, 2021 and Consumer Affairs | T84: https://www.njconsumeraffairs.gov/hic/Applications/Home-Improvement-Contractor-Application-for-Initial-Registration.pdf | U84: https://www.njconsumeraffairs.gov/renewals/Pages/default.aspx | W84: N | X84: In person,Mail,Online | Y84: In person,Mail | Z84: System Automation (SA), DCA Website | AA84: 110 | AB84: 110 | AC84: Yes | AE84: No | AG84: No | AI84: Business license. ONLINE RENEWAL | BG84: Home Improvement Contractor | BH84: Yes | BI84: Migration MLO > Dynamics in progress | BK84: JmL | BL84: Obtain Your Home Improvement Contractor Registration
A85: Registered Architect (Renewal) | B85: Department of Law and Public Safety | C85: 7648 | D85: No | G85: Renewal not rendered for users as this is an individual license without an integration | K85: Evergreen | AI85: Renewal submission volume is an average of 2020-2024 | BH85: No | BL85: Architect License Renewal Deadline
A86: Monthly Dog License Report | B86: Department of Health | C86: 7350 | S86: 2021 Permit List | V86: VPH-10 | X86: Online | Y86: Mail | Z86: NJDOH Form Website | AA86: Municipalities submit dog license fees with this form ($1 for rabies fee per dog, 0.20 for pilot clinic fee, $3 per intact dog) | AI86: Don says this is at the local level but could double-check. | AJ86: No | AK86: 0.05 | AL86: Avg 3-5 days | AM86: No | AN86: No | AO86: Yes | AP86: 2 | AQ86: No | AR86: No | AS86: No | AT86: Numbers from report don't add up to amount on check, check isn't signed | AU86: estimate | AV86: Yes
A87: Master HVACR Contractor (Renewal) | B87: Department of Law and Public Safety | C87: 7308 | D87: No | G87: Renewal not rendered for users as this is an individual license without an integration | K87: Evergreen | AI87: Renewal submission volume is an average of 2020-2024 | BH87: No | BL87: HVACR License Renewal Deadline
A88: Community Right To Know Survey | B88: Department of Environmental Protection | C88: 7217 | D88: Yes businesses often apply for this plurmit (for a device or project or something else) | E88: Submitted | F88: Yes - Low Priority Integration | G88: Integration Scenario: - Existing business onboards to B.NJ.gov -> B.NJ.gov queries CRTK db -> if Business has a compliance requirement -> then showcase prompt for next steps - Not sure if a calendar reminder would need an integration since CRTK annual reporting is a static date (march 1st) I think this would apply to businesses that create waste in the form of chemicals. Also Jess suggested for existing businesses, we could tap in to CRTK's DB and assess if they're on DEP's radar for expected compliance with CRTK. | H88: Mentioned | S88: Combined data from 2018 and 2021 | T88: https://www.nj.gov/dep/online/ | U88: https://www.nj.gov/dep/online/ | X88: Online | Y88: Online | Z88: DEP Online | AC88: No | AE88: No | AG88: No | AH88: https://www.nj.gov/dep/online/ | BP88: The document is a step-by-step guide to completing the Community Right to Know (eCRTK) Survey online. It aims to increase community awareness of chemical hazards and inform emergency response units. Key points include: Purpose: - Raise awareness of chemical hazards. - Inform emergency response units. - Surveys are due by March 1st each year and must be submitted online. Determining Exemption: - Identify chemicals with Safety Data Sheets (SDS). - Check chemicals against NJDEP’s Environmental Hazardous Substances (EHS) list. - Facilities using chemicals below reporting thresholds can apply for exemption. Exempt Facilities: - Administrative offices, non-users of hazardous chemicals, users below thresholds, unstaffed sites. - Exemption form submission and notification to local authorities required. Non-Exempt Facilities: - Facilities over reporting thresholds must complete the eCRTK survey online. Chemical Conversions: - Instructions for converting quantities of solids, liquids, mixtures, and gases to pounds. - Examples provided for each type of chemical. Setting Up NJDEP Online Account: - Instructions for creating and linking a MyNewJersey account to NJDEP online. - Steps for adding contact information and setting security questions. Adding and Managing Facilities: - Search and add facilities using an 11-digit facility identification number. - Steps for completing the setup and accessing the eCRTK survey. Completing the eCRTK Survey: - Five steps: company/facility information, substance list management, verifying data, submitting the survey, and logging out. - Emphasizes saving and printing the survey for records and notifying local authorities. Contact Information: - For questions, contact rtk@dep.nj.gov. The document provides detailed instructions for ensuring compliance with the Community Right to Know requirements in New Jersey. More context here | BQ88: Community Right to Know | BR88: https://www.nj.gov/dep/enforcement/opppc/crtk/who.html | BT88: Metal finishers,breweries,Aerial Pesticide Applicators,Food processors,lawn-care,Landscapers,cosmetology,real-estate-investor,pharmacy,retail,auto-body-repair,car-rental,car-service,courier,e-commerce,electrical-contractor,healthcare,logistics,pharmacy,printing-business,school-bus,trucking | BU88: Questionnaire | BV88: Data stored in DEP Online/NJEMS | BW88: Will your business fall under one of these industries?,Will you deliver packages by air (for example by airplane or helicopter)?,"Will you sell lawn and garden supplies, flowers, or florists’ supplies?","Will your business do management consulting services (manufacturing management, physical distribution, and site location consulting)?"
A89: Construction/Building Permit | B89: Department of Community Affairs | C89: 7000 | D89: Yes businesses often apply for this plurmit (for a device or project or something else) | F89: Yes - Mention but not Integrate | H89: Mentioned | K89: My Account Roadmap: Live | M89: Y | N89: Y | P89: Y | Q89: ? | R89: Codes and Standards (but file on local level) | T89: https://www.nj.gov/dca/divisions/codes/resources/constructionpermitforms.html | BN89: All non-home-based industries | BO89: All non-home-based industries
A90: Outdoor Advertising Permit | B90: Department of Transportation | C90: 7000 | D90: Yes businesses often apply for this plurmit (for a device or project or something else) | E90: Available | F90: Yes - Mention but not Integrate | G90: Need to connect with SME | H90: No | S90: Combined data from 2018 and 2021 | T90: https://www.state.nj.us/transportation/business/outdoor/forms.shtm | V90: OA-6 | W90: N | X90: In person,Phone,Email,Online | Y90: In person,Mail | Z90: NJDOT Website, Online as PDF | AA90: Varies | AB90: Varies | AC90: Yes | AD90: Property Owner | AE90: Yes | AG90: No
A91: Repossession, Motor Vehicles | B91: Motor Vehicle Commission | C91: 6993 | D91: Yes, but primarily used by large businesses | E91: Available | F91: No | G91: Not used by small/medium businesses | H91: No | S91: Combined data from 2018 and 2021 | T91: https://www.state.nj.us/mvc/pdf/vehicles/OS-SS-57.pdf | V91: OS/SS-57 or OS/SS-55 | W91: N | X91: Online,Phone | Y91: Mail | Z91: .Net or Java service or pdf acrobrat forms | AA91: $60 duplicate fee; $85 Lien, $25 late fee, | AB91: $60 duplicate fee; $85 Lien, $25 late fee, | AC91: Yes | AE91: No | AG91: No
A92: ABT - Alcoholic Beverages Tax | B92: Department of the Treasury | C92: 6947 | D92: Yes this is a business/shop plurmit | F92: Yes - High Priority Integration | G92: Unsure if form is actually submittable online | H92: No | R92: Division of Taxation | S92: 2021 Permit List | T92: https://www.state.nj.us/treasury/taxation/prntalcohol.shtml | V92: R-1, R-2, R-1-W, R,27, RB-1 | X92: Online | Y92: Online,Mail | AI92: Business tax. Taxation of alcohol and legal obligations businesses must meet when producing, distributing, or selling alc. Obtained by the business entity, not the individual owner. | AJ92: Yes | AK92: Cannot provide rejection counts due to daily changes. | AL92: Instantaneous | AM92: No | AN92: No | AO92: Yes | AQ92: Yes | AR92: Yes | AS92: No | AT92: Registration, Data Integrity, Calculation | AU92: 2020 & 2021 | AV92: No | BH92: Yes | BK92: JmL
A93: Asbestos Notification | B93: Department of Labor and Workforce Development | C93: 6887 | D93: Yes this is a business/shop plurmit | E93: Available | F93: Yes - Mention but not Integrate | H93: Mentioned | S93: Combined data from 2018 and 2021 | T93: https://www.nj.gov/labor/forms_pdfs/lsse/asb-41.pdf | X93: Online,Mail,Phone,In person | Y93: Mail | AA93: 200 | AB93: 200 | AC93: Yes | AE93: No | AG93: No | AI93: Business permit. Need for any asbestos removal, encapsulation, or related work. Ensures the state is informed of asbestos activities. Some asbestos webflow licenses exist but are all empty/no content. | BH93: Yes | BK93: JmL
A94: Self-Generator Solid Waste Transporters | B94: Department of Environmental Protection | C94: 6664 | D94: Yes this is a business/shop plurmit | F94: Yes - Mention but not Integrate | H94: Mentioned | BP94: Companies which transport waste generated though their own operation (“Self-Generators”) are required to complete an Initial Registration Statement to become registered and obtain decals for each piece of equipment used to transport waste. Examples of Self-Generators include: - Plumbers - Home Builders & Remodelers - Electricians - Heating, Ventilation and Air Conditioning contractors - Construction companies Self-generators are prohibited from transporting waste generated by companies or persons not directly employed by them. Furthermore the following activities are not considered self-generator and require obtaining an A901 license and a Certificate of Public Convenience and Necessity or CPCN exemption: - Clean outs, trash outs, clean ups and junk removal from homes, businesses, offices, garages, barns, sheds, warehouses, etc.; - This includes property maintenance and preservation contracts that require a clean out of waste left behind by the previous tenant or owner of the property being serviced; - Allowing other companies or persons to deposit waste they generated into a self-generator’s vehicle or container to be hauled away by the self-generator; and - Transporting waste from a demolition job that was not performed by the employees of the self-generator transporter Self-Generator Solid Waste transporters who are already registered can use the online service to obtain decals for additional equipment, obtain updated or replacement cab cards, replace lost or damaged decals, and inactivate a decal no longer being used. From Mike Gage at NJDEP: "When you have time I would like to build a journey for businesses that might wish to transport waste generated by their business such as home remodelers, roofers, and landscapers – that journey would bring them to our page for self-generator waste transporters - NJDEP| Waste Decals | Self-Generator Solid Waste Transporters – as shown below 6,664 of the 8,462 waste transporters are self-generators Their journey would have them register with Secretary of State, most would then register with Consumer Affairs as a Home Improvement Contractor, they would then register their equipment as Commercial with Motor Vehicle Commission, and then register with my groups as waste transporter. There would also be great value in building a journey for those who wish to transport waste commercially since many are small business with just a few vehicles – their journey would begin with clearing themselves with Taxation, then going to Division of Law for vetting to then get an A-901 license from my Department, then getting a Certificate of Public Convenience and Necessity from my Department, then registering with my group as a waste transporter." | BQ94: Waste | BR94: https://dep.nj.gov/wastedecals/self-generator-solid-waste-transporters/ | BT94: construction,electrical-contractor | BU94: Business Registration | BV94: Data stored in DEP Online/NJEMS | BW94: My business will transport solid/hazardous waste
A95: New Jersey Corporation Business Tax Unitary Return | B95: Department of the Treasury | C95: 6643 | D95: Yes, but primarily used by large businesses | F95: Yes - Mention but not Integrate | H95: Read | I95: https://dev.account.business.nj.gov/mgmt/cms#/collections/filings/entries/cbt-100_100u | R95: Division of Taxation | S95: 2021 Permit List | T95: https://nj.gov/treasury/taxation/prntcbt.shtml | V95: CBT-100U | X95: Online | Y95: Online | Z95: 3rd Party Software Vendor | AI95: Corporate tax filing for companies that are part of a larger group but have large presence in NJ. (ex: IBM and Verizon have operations in other states but significant business operations in NJ). Helps NJ determine how to tax them. | AJ95: Yes | AK95: Cannot provide rejection counts due to daily changes. | AL95: Instantaneous | AM95: Yes | AN95: No | AO95: Yes | AQ95: Yes | AR95: Yes | AS95: No | AT95: Registration, Data Integrity, Calculation | AU95: 2019 | AV95: No | BH95: Yes | BK95: JmL
A96: Cape May County Tourism Assessment and Tourism Fee | B96: Department of the Treasury | C96: 6465 | D96: Yes this is a business/shop plurmit | F96: High Priority Integration, lacking agency buy-in | G96: Exists in CMS https://dev.navigator.business.nj.gov/mgmt/cms#/collections/filings/entries/st-350 | H96: Read | I96: https://dev.account.business.nj.gov/mgmt/cms#/collections/filings/entries/st-350 | R96: Division of Taxation | S96: 2021 Permit List | U96: https://www1.state.nj.us/TYTR_BusinessFilings/jsp/common/Login.jsp?taxcode=71 | V96: ST-350; ST-350B | X96: Online | Y96: Online | Z96: DORES Web Portal | AI96: A business fee (vs permit/license/tax) for short-term rentals. Serves similar purpose as a tax by generating revenue, but labeled a fee bc it’s collected specifically to fund tourism-related activities rather than general gov revenue. | AJ96: Yes | AK96: Cannot provide rejection counts due to daily changes. | AL96: Instantaneous | AM96: Yes | AN96: No | AO96: Yes | AP96: DORES | AQ96: Yes | AR96: Yes | AS96: No | AT96: Registration, Data Integrity, Calculation | AU96: 2020 | AV96: No | BH96: Yes | BK96: JmL
A97: Monitoring Results Submittal | B97: Department of Environmental Protection | C97: 6417 | D97: No, this is for municipalities or residents but not businesses | E97: Submitted | F97: No | G97: The lack of information in the 2018 & 2021 data dump from DEP does not allow the team to assess this plurmit properly. Our best guess is that it relates to the DMR and WCR plurmits. Since those were deemed—no, this is for municipalities, not businesses—I will label this one the same. | H97: No | S97: Combined data from 2018 and 2021 | T97: https://www.nj.gov/dep/online/ | U97: https://www.nj.gov/dep/online/ | X97: Online | Y97: Online | Z97: DEP Online | AC97: No | AE97: No | AG97: No | AH97: https://www.nj.gov/dep/online/ | BQ97: Wastewater | BU97: Report/Logbook | BV97: Data stored in DEP Online/NJEMS
A98: TPT - Tobacco Products Tax | B98: Department of the Treasury | C98: 6369 | D98: Yes this is a business/shop plurmit | F98: Yes - Mention but not Integrate | G98: Exists in CMS https://dev.navigator.business.nj.gov/mgmt/cms#/collections/filings/entries/tpt-10 | H98: Read | I98: https://dev.account.business.nj.gov/mgmt/cms#/collections/filings/entries/tpt-10 | R98: Division of Taxation | S98: 2021 Permit List | T98: https://www.state.nj.us/treasury/taxation/pdf/other_forms/tobacco/TPT-10.pdf | V98: TP-10 | X98: Online | Y98: Online,Mail | AI98: Business tax imposed on the sale or distribution of tobacco products in NJ | AJ98: Yes | AK98: Cannot provide rejection counts due to daily changes. | AL98: Instantaneous | AM98: No | AN98: No | AO98: Yes | AQ98: Yes | AR98: Yes | AS98: No | AT98: Registration, Data Integrity, Calculation | AU98: 2020 & 2021 | AV98: No | BH98: Yes | BK98: JmL
A99: Broker-Salesperson - Renewal (2021-2023) | B99: Department of Banking and Insurance | C99: 6296 | D99: No, this is for municipalities or residents but not businesses | S99: 2021 Permit List | U99: https://www-dobi.state.nj.us/DOBI_RELOLSRV/LicenseeLogin | X99: Online | Y99: Online | Z99: NJDOBI website | AA99: 200 | AJ99: 0 | AK99: 0 | AL99: 30 | AM99: 1 | AN99: 0 | AO99: 1 | AP99: 4 | AQ99: No | AR99: 1 | AS99: No | AV99: Yes
A100: Vehicle Registration Renewal - Non Registered | B100: Department of Environmental Protection | C100: 6200 | D100: Yes this is a business/shop plurmit | E100: Submitted | F100: Yes - Mention but not Integrate | G100: NJDEP stated this renewal path is on the non-registered/authenticated experience of DEP Online because the renewal period is lengthy (2 years or five years), and requiring a business to remember login details doesn't seem like the right experience. The high number of submissions was probably taken during a renewal period. If we were to go down this integration path, at most, we could expose the expiry date for their decal in MyAccount, but initial vehicle registration counts are deemed "low": - A-901 is 80-150 a year - Solid Waste Transporter is 700-850 a year | H100: Mentioned | S100: Combined data from 2018 and 2021 | T100: https://www.nj.gov/dep/online/ | U100: https://www.nj.gov/dep/online/ | X100: Online | Y100: Online | Z100: DEP Online | AC100: No | AE100: No | AG100: No | AH100: https://www.nj.gov/dep/online/ | BP100: Tl;dr -- hauling waste within NJ | BQ100: Waste | BT100: Landscapers,lawn-care,home-contractor,Junk Removal,electrical-contractor,construction | BU100: Renewal | BV100: Data stored in DEP Online/NJEMS | BW100: My business will transport solid/hazardous waste
...

Sheet Counting - no filter on "busine
A1: Department | B1: Number of Licenses | C1: Annual Submission
A2: Board of Public Utilities | B2: =COUNTIF('Plurmits-All Plurmits'!B:B, A2) -> 5 | C2: =SUMIF('Plurmits-All Plurmits'!B:B, A2, 'Plurmits-All Plurmits'!C:C) -> 697
A3: Casino Control Commission | B3: =COUNTIF('Plurmits-All Plurmits'!B:B, A3) -> 1 | C3: =SUMIF('Plurmits-All Plurmits'!B:B, A3, 'Plurmits-All Plurmits'!C:C) -> 14094
A4: Department of Agriculture | B4: =COUNTIF('Plurmits-All Plurmits'!B:B, A4) -> 31 | C4: =SUMIF('Plurmits-All Plurmits'!B:B, A4, 'Plurmits-All Plurmits'!C:C) -> 22074
A5: Department of Banking and Insurance | B5: =COUNTIF('Plurmits-All Plurmits'!B:B, A5) -> 210 | C5: =SUMIF('Plurmits-All Plurmits'!B:B, A5, 'Plurmits-All Plurmits'!C:C) -> 876362
A6: Department of Children and Families | B6: =COUNTIF('Plurmits-All Plurmits'!B:B, A6) -> 12 | C6: =SUMIF('Plurmits-All Plurmits'!B:B, A6, 'Plurmits-All Plurmits'!C:C) -> 4991
A7: Department of Community Affairs | B7: =COUNTIF('Plurmits-All Plurmits'!B:B, A7) -> 116 | C7: =SUMIF('Plurmits-All Plurmits'!B:B, A7, 'Plurmits-All Plurmits'!C:C) -> 98450
A8: Department of Education | B8: =COUNTIF('Plurmits-All Plurmits'!B:B, A8) -> 149 | C8: =SUMIF('Plurmits-All Plurmits'!B:B, A8, 'Plurmits-All Plurmits'!C:C) -> 36845
A9: Department of Environmental Protection | B9: =COUNTIF('Plurmits-All Plurmits'!B:B, A9) -> 800 | C9: =SUMIF('Plurmits-All Plurmits'!B:B, A9, 'Plurmits-All Plurmits'!C:C) -> 751422
A10: Department of Health | B10: =COUNTIF('Plurmits-All Plurmits'!B:B, A10) -> 116 | C10: =SUMIF('Plurmits-All Plurmits'!B:B, A10, 'Plurmits-All Plurmits'!C:C) -> 68750
A11: Department of Labor and Workforce Development | B11: =COUNTIF('Plurmits-All Plurmits'!B:B, A11) -> 38 | C11: =SUMIF('Plurmits-All Plurmits'!B:B, A11, 'Plurmits-All Plurmits'!C:C) -> 150722
A12: Department of Law and Public Safety | B12: =COUNTIF('Plurmits-All Plurmits'!B:B, A12) -> 564 | C12: =SUMIF('Plurmits-All Plurmits'!B:B, A12, 'Plurmits-All Plurmits'!C:C) -> 494145
A13: Department of the Treasury | B13: =COUNTIF('Plurmits-All Plurmits'!B:B, A13) -> 81 | C13: =SUMIF('Plurmits-All Plurmits'!B:B, A13, 'Plurmits-All Plurmits'!C:C) -> 3093782
... A16: Motor Vehicle Commission | B16: =COUNTIF('Plurmits-All Plurmits'!B:B, A16) -> 42 | C16: =SUMIF('Plurmits-All Plurmits'!B:B, A16, 'Plurmits-All Plurmits'!C:C) -> 317751
C17: =SUMIF('Plurmits-All Plurmits'!B:B, A17, 'Plurmits-All Plurmits'!C:C) -> 0
B18: =SUM(B2:B17) -> 2185 | C18: =SUMIF('Plurmits-All Plurmits'!B:B, A18, 'Plurmits-All Plurmits'!C:C) -> 0

Sheet Pivot - filtered to business
A1: Does this plurmit apply to businesses? | B1: (Multiple Items)
A4: Department | B4: SUM of Annual volume of submissions | C4: COUNT of Annual volume of submissions
A5: Casino Control Commission | B5: 14094 | C5: 1
A6: Department of Banking and Insurance | B6: 696576 | C6: 5
A7: Department of Community Affairs | B7: 65604 | C7: 43
A8: Department of Environmental Protection | B8: 158335 | C8: 91
A9: Department of Labor and Workforce Development | B9: 132969 | C9: 6
A10: Department of Law and Public Safety | B10: 397107 | C10: 125
A11: Department of the Treasury | B11: 3058257 | C11: 63
A12: Department of Transportation | B12: 118905 | C12: 6
A13: Division of Alcohol Division Control | B13: 63365 | C13: 2
A14: Motor Vehicle Commission | B14: 307063 | C14: 11
A15: Grand Total | B15: 5012275 | C15: 353
